{"dados":[{"ano":2021,"mes":1,"tipoDespesa":"MANUTENÇÃO DE ESCRITÓRIO DE APOIO À ATIVIDADE PARLAMENTAR","codDocumento":7154400,"tipoDocumento":"Recibos/Outros","codTipoDocumento":1,"dataDocumento":"2021-01-31","numDocumento":"01","valorDocumento":2400.0,"urlDocumento":"https://www.camara.leg.br/cota-parlamentar/documentos/publ/2235/2021/7154400.pdf","nomeFornecedor":"ANTONIO EUGENIO SOCORRO FERNANDES","cnpjCpfFornecedor":"29288428615","valorLiquido":2400.0,"valorGlosa":0.0,"numRessarcimento":"","codLote":1745486,"parcela":0},{"ano":2021,"mes":3,"tipoDespesa":"MANUTENÇÃO DE ESCRITÓRIO DE APOIO À ATIVIDADE PARLAMENTAR","codDocumento":7178847,"tipoDocumento":"Recibos/Outros","codTipoDocumento":1,"dataDocumento":"2021-03-31","numDocumento":"032021","valorDocumento":2400.0,"urlDocumento":"https://www.camara.leg.br/cota-parlamentar/documentos/publ/2235/2021/7178847.pdf","nomeFornecedor":"ANTONIO EUGENIO SOCORRO FERNANDES","cnpjCpfFornecedor":"29288428615","valorLiquido":2400.0,"valorGlosa":0.0,"numRessarcimento":"","codLote":1758154,"parcela":0},{"ano":2021,"mes":5,"tipoDespesa":"MANUTENÇÃO DE ESCRITÓRIO DE APOIO À ATIVIDADE PARLAMENTAR","codDocumento":7221439,"tipoDocumento":"Recibos/Outros","codTipoDocumento":1,"dataDocumento":"2021-05-31","numDocumento":"052021","valorDocumento":2400.0,"urlDocumento":"https://www.camara.leg.br/cota-parlamentar/documentos/publ/2235/2021/7221439.pdf","nomeFornecedor":"ANTONIO EUGENIO SOCORRO FERNANDES","cnpjCpfFornecedor":"29288428615","valorLiquido":2400.0,"valorGlosa":0.0,"numRessarcimento":"","codLote":1778712,"parcela":0},{"ano":2021,"mes":7,"tipoDespesa":"MANUTENÇÃO DE ESCRITÓRIO DE APOIO À ATIVIDADE PARLAMENTAR","codDocumento":7251098,"tipoDocumento":"Recibos/Outros","codTipoDocumento":1,"dataDocumento":"2021-07-31","numDocumento":"07","valorDocumento":2400.0,"urlDocumento":"https://www.camara.leg.br/cota-parlamentar/documentos/publ/2235/2021/7251098.pdf","nomeFornecedor":"ANTONIO EUGENIO SOCORRO FERNANDES","cnpjCpfFornecedor":"29288428615","valorLiquido":2400.0,"valorGlosa":0.0,"numRessarcimento":"","codLote":1792148,"parcela":0},{"ano":2021,"mes":8,"tipoDespesa":"MANUTENÇÃO DE ESCRITÓRIO DE APOIO À ATIVIDADE PARLAMENTAR","codDocumento":7257439,"tipoDocumento":"Recibos/Outros","codTipoDocumento":1,"dataDocumento":"2021-08-31","numDocumento":"08","valorDocumento":2400.0,"urlDocumento":"https://www.camara.leg.br/cota-parlamentar/documentos/publ/2235/2021/7257439.pdf","nomeFornecedor":"ANTONIO EUGENIO SOCORRO FERNANDES","cnpjCpfFornecedor":"29288428615","valorLiquido":2400.0,"valorGlosa":0.0,"numRessarcimento":"","codLote":1795016,"parcela":0},{"ano":2021,"mes":9,"tipoDespesa":"MANUTENÇÃO DE ESCRITÓRIO DE APOIO À ATIVIDADE PARLAMENTAR","codDocumento":7273970,"tipoDocumento":"Recibos/Outros","codTipoDocumento":1,"dataDocumento":"2021-09-30","numDocumento":"092021","valorDocumento":2400.0,"urlDocumento":"https://www.camara.leg.br/cota-parlamentar/documentos/publ/2235/2021/7273970.pdf","nomeFornecedor":"ANTONIO EUGENIO SOCORRO FERNANDES","cnpjCpfFornecedor":"29288428615","valorLiquido":2400.0,"valorGlosa":0.0,"numRessarcimento":"","codLote":1802374,"parcela":0},{"ano":2021,"mes":10,"tipoDespesa":"MANUTENÇÃO DE ESCRITÓRIO DE APOIO À ATIVIDADE PARLAMENTAR","codDocumento":7289287,"tipoDocumento":"Recibos/Outros","codTipoDocumento":1,"dataDocumento":"2021-11-17","numDocumento":"10/2021","valorDocumento":2400.0,"urlDocumento":"https://www.camara.leg.br/cota-parlamentar/documentos/publ/2235/2021/7289287.pdf","nomeFornecedor":"ANTONIO EUGENIO SOCORRO FERNANDES","cnpjCpfFornecedor":"29288428615","valorLiquido":2400.0,"valorGlosa":0.0,"numRessarcimento":"","codLote":1809533,"parcela":0},{"ano":2021,"mes":2,"tipoDespesa":"MANUTENÇÃO DE ESCRITÓRIO DE APOIO À ATIVIDADE PARLAMENTAR","codDocumento":7167863,"tipoDocumento":"Recibos/Outros","codTipoDocumento":1,"dataDocumento":"2021-02-28","numDocumento":"2/2021","valorDocumento":2400.0,"urlDocumento":"https://www.camara.leg.br/cota-parlamentar/documentos/publ/2235/2021/7167863.pdf","nomeFornecedor":"ANTONIO EUGENIO SOCORRO FERNANDES","cnpjCpfFornecedor":"29288428615","valorLiquido":2400.0,"valorGlosa":0.0,"numRessarcimento":"","codLote":1752535,"parcela":0},{"ano":2021,"mes":4,"tipoDespesa":"MANUTENÇÃO DE ESCRITÓRIO DE APOIO À ATIVIDADE PARLAMENTAR","codDocumento":7192241,"tipoDocumento":"Recibos/Outros","codTipoDocumento":1,"dataDocumento":"2021-05-11","numDocumento":"4/2021","valorDocumento":2400.0,"urlDocumento":"https://www.camara.leg.br/cota-parlamentar/documentos/publ/2235/2021/7192241.pdf","nomeFornecedor":"ANTONIO EUGENIO SOCORRO FERNANDES","cnpjCpfFornecedor":"29288428615","valorLiquido":2400.0,"valorGlosa":0.0,"numRessarcimento":"","codLote":1764370,"parcela":0},{"ano":2021,"mes":6,"tipoDespesa":"MANUTENÇÃO DE ESCRITÓRIO DE APOIO À ATIVIDADE PARLAMENTAR","codDocumento":7223858,"tipoDocumento":"Recibos/Outros","codTipoDocumento":1,"dataDocumento":"2021-06-30","numDocumento":"6","valorDocumento":2400.0,"urlDocumento":"https://www.camara.leg.br/cota-parlamentar/documentos/publ/2235/2021/7223858.pdf","nomeFornecedor":"ANTONIO EUGENIO SOCORRO FERNANDES","cnpjCpfFornecedor":"29288428615","valorLiquido":2400.0,"valorGlosa":0.0,"numRessarcimento":"","codLote":1779823,"parcela":0},{"ano":2021,"mes":1,"tipoDespesa":"MANUTENÇÃO DE ESCRITÓRIO DE APOIO À ATIVIDADE PARLAMENTAR","codDocumento":7153409,"tipoDocumento":"Recibos/Outros","codTipoDocumento":1,"dataDocumento":"2021-02-09","numDocumento":"1017","valorDocumento":400.0,"urlDocumento":"https://www.camara.leg.br/cota-parlamentar/documentos/publ/2235/2021/7153409.pdf","nomeFornecedor":"APA  INFORMÁTICA E TELECOMUNICAÇÕES LTDA-PRODATEL","cnpjCpfFornecedor":"18268318000113","valorLiquido":400.0,"valorGlosa":0.0,"numRessarcimento":"","codLote":1744968,"parcela":0},{"ano":2021,"mes":2,"tipoDespesa":"MANUTENÇÃO DE ESCRITÓRIO DE APOIO À ATIVIDADE PARLAMENTAR","codDocumento":7167869,"tipoDocumento":"Recibos/Outros","codTipoDocumento":1,"dataDocumento":"2021-03-09","numDocumento":"1018","valorDocumento":400.0,"urlDocumento":"https://www.camara.leg.br/cota-parlamentar/documentos/publ/2235/2021/7167869.pdf","nomeFornecedor":"APA  INFORMÁTICA E TELECOMUNICAÇÕES LTDA-PRODATEL","cnpjCpfFornecedor":"18268318000113","valorLiquido":400.0,"valorGlosa":0.0,"numRessarcimento":"","codLote":1752534,"parcela":0},{"ano":2021,"mes":4,"tipoDespesa":"MANUTENÇÃO DE ESCRITÓRIO DE APOIO À ATIVIDADE PARLAMENTAR","codDocumento":7205703,"tipoDocumento":"Recibos/Outros","codTipoDocumento":1,"dataDocumento":"2021-05-13","numDocumento":"1020","valorDocumento":400.0,"urlDocumento":"https://www.camara.leg.br/cota-parlamentar/documentos/publ/2235/2021/7205703.pdf","nomeFornecedor":"APA  INFORMÁTICA E TELECOMUNICAÇÕES LTDA-PRODATEL","cnpjCpfFornecedor":"18268318000113","valorLiquido":400.0,"valorGlosa":0.0,"numRessarcimento":"","codLote":1770655,"parcela":0},{"ano":2021,"mes":5,"tipoDespesa":"MANUTENÇÃO DE ESCRITÓRIO DE APOIO À ATIVIDADE PARLAMENTAR","codDocumento":7221538,"tipoDocumento":"Recibos/Outros","codTipoDocumento":1,"dataDocumento":"2021-06-09","numDocumento":"1021","valorDocumento":400.0,"urlDocumento":"https://www.camara.leg.br/cota-parlamentar/documentos/publ/2235/2021/7221538.pdf","nomeFornecedor":"APA  INFORMÁTICA E TELECOMUNICAÇÕES LTDA-PRODATEL","cnpjCpfFornecedor":"18268318000113","valorLiquido":400.0,"valorGlosa":0.0,"numRessarcimento":"","codLote":1778711,"parcela":0},{"ano":2021,"mes":6,"tipoDespesa":"MANUTENÇÃO DE ESCRITÓRIO DE APOIO À ATIVIDADE PARLAMENTAR","codDocumento":7223900,"tipoDocumento":"Nota Fiscal","codTipoDocumento":0,"dataDocumento":"2021-07-09","numDocumento":"1022","valorDocumento":400.0,"urlDocumento":"https://www.camara.leg.br/cota-parlamentar/documentos/publ/2235/2021/7223900.pdf","nomeFornecedor":"APA  INFORMÁTICA E TELECOMUNICAÇÕES LTDA-PRODATEL","cnpjCpfFornecedor":"18268318000113","valorLiquido":400.0,"valorGlosa":0.0,"numRessarcimento":"","codLote":1779825,"parcela":0},{"ano":2021,"mes":7,"tipoDespesa":"MANUTENÇÃO DE ESCRITÓRIO DE APOIO À ATIVIDADE PARLAMENTAR","codDocumento":7251131,"tipoDocumento":"Recibos/Outros","codTipoDocumento":1,"dataDocumento":"2021-08-09","numDocumento":"1023","valorDocumento":400.0,"urlDocumento":"https://www.camara.leg.br/cota-parlamentar/documentos/publ/2235/2021/7251131.pdf","nomeFornecedor":"APA  INFORMÁTICA E TELECOMUNICAÇÕES LTDA-PRODATEL","cnpjCpfFornecedor":"18268318000113","valorLiquido":400.0,"valorGlosa":0.0,"numRessarcimento":"","codLote":1792147,"parcela":0},{"ano":2021,"mes":8,"tipoDespesa":"MANUTENÇÃO DE ESCRITÓRIO DE APOIO À ATIVIDADE PARLAMENTAR","codDocumento":7274008,"tipoDocumento":"Recibos/Outros","codTipoDocumento":1,"dataDocumento":"2021-09-09","numDocumento":"1024","valorDocumento":400.0,"urlDocumento":"https://www.camara.leg.br/cota-parlamentar/documentos/publ/2235/2021/7274008.pdf","nomeFornecedor":"APA  INFORMÁTICA E TELECOMUNICAÇÕES LTDA-PRODATEL","cnpjCpfFornecedor":"18268318000113","valorLiquido":400.0,"valorGlosa":0.0,"numRessarcimento":"","codLote":1802371,"parcela":0},{"ano":2021,"mes":9,"tipoDespesa":"MANUTENÇÃO DE ESCRITÓRIO DE APOIO À ATIVIDADE PARLAMENTAR","codDocumento":7280435,"tipoDocumento":"Recibos/Outros","codTipoDocumento":1,"dataDocumento":"2021-10-08","numDocumento":"1025","valorDocumento":400.0,"urlDocumento":"https://www.camara.leg.br/cota-parlamentar/documentos/publ/2235/2021/7280435.pdf","nomeFornecedor":"APA  INFORMÁTICA E TELECOMUNICAÇÕES LTDA-PRODATEL","cnpjCpfFornecedor":"18268318000113","valorLiquido":400.0,"valorGlosa":0.0,"numRessarcimento":"","codLote":1805365,"parcela":0},{"ano":2021,"mes":10,"tipoDespesa":"MANUTENÇÃO DE ESCRITÓRIO DE APOIO À ATIVIDADE PARLAMENTAR","codDocumento":7286075,"tipoDocumento":"Recibos/Outros","codTipoDocumento":1,"dataDocumento":"2021-11-08","numDocumento":"1026","valorDocumento":400.0,"urlDocumento":"https://www.camara.leg.br/cota-parlamentar/documentos/publ/2235/2021/7286075.pdf","nomeFornecedor":"APA  INFORMÁTICA E TELECOMUNICAÇÕES LTDA-PRODATEL","cnpjCpfFornecedor":"18268318000113","valorLiquido":400.0,"valorGlosa":0.0,"numRessarcimento":"","codLote":1807782,"parcela":0},{"ano":2021,"mes":12,"tipoDespesa":"MANUTENÇÃO DE ESCRITÓRIO DE APOIO À ATIVIDADE PARLAMENTAR","codDocumento":7316296,"tipoDocumento":"Recibos/Outros","codTipoDocumento":1,"dataDocumento":"2022-01-09","numDocumento":"1028","valorDocumento":400.0,"urlDocumento":"https://www.camara.leg.br/cota-parlamentar/documentos/publ/2235/2022/7316296.pdf","nomeFornecedor":"APA  INFORMÁTICA E TELECOMUNICAÇÕES LTDA-PRODATEL","cnpjCpfFornecedor":"18268318000113","valorLiquido":400.0,"valorGlosa":0.0,"numRessarcimento":"","codLote":1830619,"parcela":0},{"ano":2021,"mes":3,"tipoDespesa":"MANUTENÇÃO DE ESCRITÓRIO DE APOIO À ATIVIDADE PARLAMENTAR","codDocumento":7178921,"tipoDocumento":"Recibos/Outros","codTipoDocumento":1,"dataDocumento":"2021-04-13","numDocumento":"1019","valorDocumento":400.0,"urlDocumento":"https://www.camara.leg.br/cota-parlamentar/documentos/publ/2235/2021/7178921.pdf","nomeFornecedor":"APA INFORMATICA E TELECOMUNICACOES LTDA","cnpjCpfFornecedor":"18268318000113","valorLiquido":400.0,"valorGlosa":0.0,"numRessarcimento":"","codLote":1758153,"parcela":0},{"ano":2021,"mes":11,"tipoDespesa":"MANUTENÇÃO DE ESCRITÓRIO DE APOIO À ATIVIDADE PARLAMENTAR","codDocumento":7302740,"tipoDocumento":"Recibos/Outros","codTipoDocumento":1,"dataDocumento":"2021-12-09","numDocumento":"1027","valorDocumento":400.0,"urlDocumento":"https://www.camara.leg.br/cota-parlamentar/documentos/publ/2235/2021/7302740.pdf","nomeFornecedor":"APA INFORMATICA E TELECOMUNICACOES LTDA","cnpjCpfFornecedor":"18268318000113","valorLiquido":400.0,"valorGlosa":0.0,"numRessarcimento":"","codLote":1815394,"parcela":0},{"ano":2021,"mes":1,"tipoDespesa":"MANUTENÇÃO DE ESCRITÓRIO DE APOIO À ATIVIDADE PARLAMENTAR","codDocumento":7144168,"tipoDocumento":"Nota Fiscal","codTipoDocumento":0,"dataDocumento":"2021-01-05","numDocumento":"052578031","valorDocumento":157.36,"urlDocumento":null,"nomeFornecedor":"CEMIG DISTRIBUIÇÃO S.A.","cnpjCpfFornecedor":"06981180000116","valorLiquido":157.36,"valorGlosa":0.0,"numRessarcimento":"","codLote":1740399,"parcela":0},{"ano":2021,"mes":1,"tipoDespesa":"MANUTENÇÃO DE ESCRITÓRIO DE APOIO À ATIVIDADE PARLAMENTAR","codDocumento":7162443,"tipoDocumento":"Nota Fiscal","codTipoDocumento":0,"dataDocumento":"2021-01-26","numDocumento":"053630035","valorDocumento":42.07,"urlDocumento":null,"nomeFornecedor":"CEMIG DISTRIBUIÇÃO S.A.","cnpjCpfFornecedor":"06981180000116","valorLiquido":39.24,"valorGlosa":2.83,"numRessarcimento":"","codLote":1749396,"parcela":0},{"ano":2021,"mes":1,"tipoDespesa":"MANUTENÇÃO DE ESCRITÓRIO DE APOIO À ATIVIDADE PARLAMENTAR","codDocumento":7162446,"tipoDocumento":"Nota Fiscal","codTipoDocumento":0,"dataDocumento":"2021-01-26","numDocumento":"053630036","valorDocumento":194.23,"urlDocumento":null,"nomeFornecedor":"CEMIG DISTRIBUIÇÃO S.A.","cnpjCpfFornecedor":"06981180000116","valorLiquido":187.03,"valorGlosa":7.2,"numRessarcimento":"","codLote":1749396,"parcela":0},{"ano":2021,"mes":2,"tipoDespesa":"MANUTENÇÃO DE ESCRITÓRIO DE APOIO À ATIVIDADE PARLAMENTAR","codDocumento":7174528,"tipoDocumento":"Nota Fiscal","codTipoDocumento":0,"dataDocumento":"2021-02-25","numDocumento":"055118513","valorDocumento":109.85,"urlDocumento":null,"nomeFornecedor":"CEMIG DISTRIBUIÇÃO S.A.","cnpjCpfFornecedor":"06981180000116","valorLiquido":109.85,"valorGlosa":0.0,"numRessarcimento":"","codLote":1755985,"parcela":0},{"ano":2021,"mes":2,"tipoDespesa":"MANUTENÇÃO DE ESCRITÓRIO DE APOIO À ATIVIDADE PARLAMENTAR","codDocumento":7174522,"tipoDocumento":"Nota Fiscal","codTipoDocumento":0,"dataDocumento":"2021-02-25","numDocumento":"055118514","valorDocumento":288.02,"urlDocumento":null,"nomeFornecedor":"CEMIG DISTRIBUIÇÃO S.A.","cnpjCpfFornecedor":"06981180000116","valorLiquido":288.02,"valorGlosa":0.0,"numRessarcimento":"","codLote":1755985,"parcela":0},{"ano":2021,"mes":3,"tipoDespesa":"MANUTENÇÃO DE ESCRITÓRIO DE APOIO À ATIVIDADE PARLAMENTAR","codDocumento":7174533,"tipoDocumento":"Nota Fiscal","codTipoDocumento":0,"dataDocumento":"2021-03-04","numDocumento":"055330342","valorDocumento":148.74,"urlDocumento":null,"nomeFornecedor":"CEMIG DISTRIBUIÇÃO S.A.","cnpjCpfFornecedor":"06981180000116","valorLiquido":148.74,"valorGlosa":0.0,"numRessarcimento":"","codLote":1755986,"parcela":0},{"ano":2021,"mes":3,"tipoDespesa":"MANUTENÇÃO DE ESCRITÓRIO DE APOIO À ATIVIDADE PARLAMENTAR","codDocumento":7187059,"tipoDocumento":"Nota Fiscal","codTipoDocumento":0,"dataDocumento":"2021-03-26","numDocumento":"056542071","valorDocumento":77.74,"urlDocumento":null,"nomeFornecedor":"CEMIG DISTRIBUIÇÃO S.A.","cnpjCpfFornecedor":"06981180000116","valorLiquido":77.74,"valorGlosa":0.0,"numRessarcimento":"","codLote":1761934,"parcela":0},{"ano":2021,"mes":3,"tipoDespesa":"MANUTENÇÃO DE ESCRITÓRIO DE APOIO À ATIVIDADE PARLAMENTAR","codDocumento":7187067,"tipoDocumento":"Nota Fiscal","codTipoDocumento":0,"dataDocumento":"2021-03-26","numDocumento":"056542072","valorDocumento":243.1,"urlDocumento":null,"nomeFornecedor":"CEMIG DISTRIBUIÇÃO S.A.","cnpjCpfFornecedor":"06981180000116","valorLiquido":243.1,"valorGlosa":0.0,"numRessarcimento":"","codLote":1761934,"parcela":0},{"ano":2021,"mes":4,"tipoDespesa":"MANUTENÇÃO DE ESCRITÓRIO DE APOIO À ATIVIDADE PARLAMENTAR","codDocumento":7187063,"tipoDocumento":"Nota Fiscal","codTipoDocumento":0,"dataDocumento":"2021-04-06","numDocumento":"056771932","valorDocumento":86.86,"urlDocumento":null,"nomeFornecedor":"CEMIG DISTRIBUIÇÃO S.A.","cnpjCpfFornecedor":"06981180000116","valorLiquido":86.86,"valorGlosa":0.0,"numRessarcimento":"","codLote":1761935,"parcela":0},{"ano":2021,"mes":4,"tipoDespesa":"MANUTENÇÃO DE ESCRITÓRIO DE APOIO À ATIVIDADE PARLAMENTAR","codDocumento":7205682,"tipoDocumento":"Nota Fiscal","codTipoDocumento":0,"dataDocumento":"2021-04-24","numDocumento":"057866992","valorDocumento":188.17,"urlDocumento":null,"nomeFornecedor":"CEMIG DISTRIBUIÇÃO S.A.","cnpjCpfFornecedor":"06981180000116","valorLiquido":188.17,"valorGlosa":0.0,"numRessarcimento":"","codLote":1770655,"parcela":0},{"ano":2021,"mes":5,"tipoDespesa":"MANUTENÇÃO DE ESCRITÓRIO DE APOIO À ATIVIDADE PARLAMENTAR","codDocumento":7205679,"tipoDocumento":"Nota Fiscal","codTipoDocumento":0,"dataDocumento":"2021-05-04","numDocumento":"058191244","valorDocumento":109.66,"urlDocumento":null,"nomeFornecedor":"CEMIG DISTRIBUIÇÃO S.A.","cnpjCpfFornecedor":"06981180000116","valorLiquido":109.66,"valorGlosa":0.0,"numRessarcimento":"","codLote":1770657,"parcela":0},{"ano":2021,"mes":5,"tipoDespesa":"MANUTENÇÃO DE ESCRITÓRIO DE APOIO À ATIVIDADE PARLAMENTAR","codDocumento":7221421,"tipoDocumento":"Nota Fiscal","codTipoDocumento":0,"dataDocumento":"2021-05-25","numDocumento":"059318704","valorDocumento":72.95,"urlDocumento":null,"nomeFornecedor":"CEMIG DISTRIBUIÇÃO S.A.","cnpjCpfFornecedor":"06981180000116","valorLiquido":72.95,"valorGlosa":0.0,"numRessarcimento":"","codLote":1778711,"parcela":0},{"ano":2021,"mes":5,"tipoDespesa":"MANUTENÇÃO DE ESCRITÓRIO DE APOIO À ATIVIDADE PARLAMENTAR","codDocumento":7221417,"tipoDocumento":"Nota Fiscal","codTipoDocumento":0,"dataDocumento":"2021-05-25","numDocumento":"059318705","valorDocumento":232.11,"urlDocumento":null,"nomeFornecedor":"CEMIG DISTRIBUIÇÃO S.A.","cnpjCpfFornecedor":"06981180000116","valorLiquido":232.11,"valorGlosa":0.0,"numRessarcimento":"","codLote":1778711,"parcela":0},{"ano":2021,"mes":6,"tipoDespesa":"MANUTENÇÃO DE ESCRITÓRIO DE APOIO À ATIVIDADE PARLAMENTAR","codDocumento":7221426,"tipoDocumento":"Nota Fiscal","codTipoDocumento":0,"dataDocumento":"2021-06-02","numDocumento":"059628953","valorDocumento":113.49,"urlDocumento":null,"nomeFornecedor":"CEMIG DISTRIBUIÇÃO S.A.","cnpjCpfFornecedor":"06981180000116","valorLiquido":113.49,"valorGlosa":0.0,"numRessarcimento":"","codLote":1778713,"parcela":0},{"ano":2021,"mes":6,"tipoDespesa":"MANUTENÇÃO DE ESCRITÓRIO DE APOIO À ATIVIDADE PARLAMENTAR","codDocumento":7240768,"tipoDocumento":"Nota Fiscal","codTipoDocumento":0,"dataDocumento":"2021-06-24","numDocumento":"060768583","valorDocumento":41.94,"urlDocumento":null,"nomeFornecedor":"CEMIG DISTRIBUIÇÃO S.A.","cnpjCpfFornecedor":"06981180000116","valorLiquido":41.94,"valorGlosa":0.0,"numRessarcimento":"","codLote":1787373,"parcela":0},{"ano":2021,"mes":6,"tipoDespesa":"MANUTENÇÃO DE ESCRITÓRIO DE APOIO À ATIVIDADE PARLAMENTAR","codDocumento":7240765,"tipoDocumento":"Nota Fiscal","codTipoDocumento":0,"dataDocumento":"2021-06-24","numDocumento":"060768584","valorDocumento":232.04,"urlDocumento":null,"nomeFornecedor":"CEMIG DISTRIBUIÇÃO S.A.","cnpjCpfFornecedor":"06981180000116","valorLiquido":232.04,"valorGlosa":0.0,"numRessarcimento":"","codLote":1787373,"parcela":0},{"ano":2021,"mes":7,"tipoDespesa":"MANUTENÇÃO DE ESCRITÓRIO DE APOIO À ATIVIDADE PARLAMENTAR","codDocumento":7240756,"tipoDocumento":"Nota Fiscal","codTipoDocumento":0,"dataDocumento":"2021-07-02","numDocumento":"061080110","valorDocumento":100.81,"urlDocumento":null,"nomeFornecedor":"CEMIG DISTRIBUIÇÃO S.A.","cnpjCpfFornecedor":"06981180000116","valorLiquido":100.81,"valorGlosa":0.0,"numRessarcimento":"","codLote":1787374,"parcela":0},{"ano":2021,"mes":8,"tipoDespesa":"MANUTENÇÃO DE ESCRITÓRIO DE APOIO À ATIVIDADE PARLAMENTAR","codDocumento":7251027,"tipoDocumento":"Nota Fiscal","codTipoDocumento":0,"dataDocumento":"2021-09-03","numDocumento":"062533851","valorDocumento":91.08,"urlDocumento":null,"nomeFornecedor":"CEMIG DISTRIBUIÇÃO S.A.","cnpjCpfFornecedor":"06981180000116","valorLiquido":91.08,"valorGlosa":0.0,"numRessarcimento":"","codLote":1792149,"parcela":0},{"ano":2021,"mes":8,"tipoDespesa":"MANUTENÇÃO DE ESCRITÓRIO DE APOIO À ATIVIDADE PARLAMENTAR","codDocumento":7274002,"tipoDocumento":"Nota Fiscal","codTipoDocumento":0,"dataDocumento":"2021-09-25","numDocumento":"063779235","valorDocumento":68.72,"urlDocumento":null,"nomeFornecedor":"CEMIG DISTRIBUIÇÃO S.A.","cnpjCpfFornecedor":"06981180000116","valorLiquido":68.72,"valorGlosa":0.0,"numRessarcimento":"","codLote":1802371,"parcela":0},{"ano":2021,"mes":8,"tipoDespesa":"MANUTENÇÃO DE ESCRITÓRIO DE APOIO À ATIVIDADE PARLAMENTAR","codDocumento":7274004,"tipoDocumento":"Nota Fiscal","codTipoDocumento":0,"dataDocumento":"2021-08-25","numDocumento":"063779236","valorDocumento":189.72,"urlDocumento":null,"nomeFornecedor":"CEMIG DISTRIBUIÇÃO S.A.","cnpjCpfFornecedor":"06981180000116","valorLiquido":189.72,"valorGlosa":0.0,"numRessarcimento":"","codLote":1802371,"parcela":0},{"ano":2021,"mes":9,"tipoDespesa":"MANUTENÇÃO DE ESCRITÓRIO DE APOIO À ATIVIDADE PARLAMENTAR","codDocumento":7274005,"tipoDocumento":"Nota Fiscal","codTipoDocumento":0,"dataDocumento":"2021-09-03","numDocumento":"064164349","valorDocumento":137.55,"urlDocumento":null,"nomeFornecedor":"CEMIG DISTRIBUIÇÃO S.A.","cnpjCpfFornecedor":"06981180000116","valorLiquido":137.55,"valorGlosa":0.0,"numRessarcimento":"","codLote":1802373,"parcela":0},{"ano":2021,"mes":9,"tipoDespesa":"MANUTENÇÃO DE ESCRITÓRIO DE APOIO À ATIVIDADE PARLAMENTAR","codDocumento":7280352,"tipoDocumento":"Nota Fiscal","codTipoDocumento":0,"dataDocumento":"2021-09-27","numDocumento":"065373923","valorDocumento":130.02,"urlDocumento":null,"nomeFornecedor":"CEMIG DISTRIBUIÇÃO S.A.","cnpjCpfFornecedor":"06981180000116","valorLiquido":130.02,"valorGlosa":0.0,"numRessarcimento":"","codLote":1805365,"parcela":0},{"ano":2021,"mes":9,"tipoDespesa":"MANUTENÇÃO DE ESCRITÓRIO DE APOIO À ATIVIDADE PARLAMENTAR","codDocumento":7280358,"tipoDocumento":"Nota Fiscal","codTipoDocumento":0,"dataDocumento":"2021-09-27","numDocumento":"065373924","valorDocumento":384.88,"urlDocumento":null,"nomeFornecedor":"CEMIG DISTRIBUIÇÃO S.A.","cnpjCpfFornecedor":"06981180000116","valorLiquido":384.88,"valorGlosa":0.0,"numRessarcimento":"","codLote":1805365,"parcela":0},{"ano":2021,"mes":10,"tipoDespesa":"MANUTENÇÃO DE ESCRITÓRIO DE APOIO À ATIVIDADE PARLAMENTAR","codDocumento":7280343,"tipoDocumento":"Nota Fiscal","codTipoDocumento":0,"dataDocumento":"2021-10-04","numDocumento":"065646929","valorDocumento":201.55,"urlDocumento":null,"nomeFornecedor":"CEMIG DISTRIBUIÇÃO S.A.","cnpjCpfFornecedor":"06981180000116","valorLiquido":201.55,"valorGlosa":0.0,"numRessarcimento":"","codLote":1805385,"parcela":0},{"ano":2021,"mes":10,"tipoDespesa":"MANUTENÇÃO DE ESCRITÓRIO DE APOIO À ATIVIDADE PARLAMENTAR","codDocumento":7298741,"tipoDocumento":"Nota Fiscal","codTipoDocumento":0,"dataDocumento":"2021-10-27","numDocumento":"067022743","valorDocumento":86.23,"urlDocumento":null,"nomeFornecedor":"CEMIG DISTRIBUIÇÃO S.A.","cnpjCpfFornecedor":"06981180000116","valorLiquido":86.23,"valorGlosa":0.0,"numRessarcimento":"","codLote":1813365,"parcela":0},{"ano":2021,"mes":10,"tipoDespesa":"MANUTENÇÃO DE ESCRITÓRIO DE APOIO À ATIVIDADE PARLAMENTAR","codDocumento":7298736,"tipoDocumento":"Nota Fiscal","codTipoDocumento":0,"dataDocumento":"2021-10-27","numDocumento":"067022744","valorDocumento":320.85,"urlDocumento":null,"nomeFornecedor":"CEMIG DISTRIBUIÇÃO S.A.","cnpjCpfFornecedor":"06981180000116","valorLiquido":320.85,"valorGlosa":0.0,"numRessarcimento":"","codLote":1813365,"parcela":0},{"ano":2021,"mes":11,"tipoDespesa":"MANUTENÇÃO DE ESCRITÓRIO DE APOIO À ATIVIDADE PARLAMENTAR","codDocumento":7298730,"tipoDocumento":"Nota Fiscal","codTipoDocumento":0,"dataDocumento":"2021-11-03","numDocumento":"067267153","valorDocumento":173.35,"urlDocumento":null,"nomeFornecedor":"CEMIG DISTRIBUIÇÃO S.A.","cnpjCpfFornecedor":"06981180000116","valorLiquido":173.35,"valorGlosa":0.0,"numRessarcimento":"","codLote":1813370,"parcela":0},{"ano":2021,"mes":2,"tipoDespesa":"MANUTENÇÃO DE ESCRITÓRIO DE APOIO À ATIVIDADE PARLAMENTAR","codDocumento":7162440,"tipoDocumento":"Nota Fiscal","codTipoDocumento":0,"dataDocumento":"2021-02-02","numDocumento":"53966813","valorDocumento":105.95,"urlDocumento":null,"nomeFornecedor":"CEMIG DISTRIBUIÇÃO S.A.","cnpjCpfFornecedor":"06981180000116","valorLiquido":105.95,"valorGlosa":0.0,"numRessarcimento":"","codLote":1749400,"parcela":0},{"ano":2021,"mes":7,"tipoDespesa":"MANUTENÇÃO DE ESCRITÓRIO DE APOIO À ATIVIDADE PARLAMENTAR","codDocumento":7251031,"tipoDocumento":"Nota Fiscal","codTipoDocumento":0,"dataDocumento":"2021-07-23","numDocumento":"62250943","valorDocumento":211.85,"urlDocumento":null,"nomeFornecedor":"CEMIG DISTRIBUIÇÃO S.A.","cnpjCpfFornecedor":"06981180000116","valorLiquido":211.85,"valorGlosa":0.0,"numRessarcimento":"","codLote":1792147,"parcela":0},{"ano":2021,"mes":10,"tipoDespesa":"MANUTENÇÃO DE ESCRITÓRIO DE APOIO À ATIVIDADE PARLAMENTAR","codDocumento":7277498,"tipoDocumento":"Nota Fiscal","codTipoDocumento":0,"dataDocumento":"2021-10-27","numDocumento":"42096","valorDocumento":199.9,"urlDocumento":"https://www.camara.leg.br/cota-parlamentar/documentos/publ/2235/2021/7277498.pdf","nomeFornecedor":"COMERCIAL NORTE ARTIGOS DE PAPELARIA EIRELI","cnpjCpfFornecedor":"24925409000187","valorLiquido":199.9,"valorGlosa":0.0,"numRessarcimento":"","codLote":1805371,"parcela":0},{"ano":2021,"mes":1,"tipoDespesa":"MANUTENÇÃO DE ESCRITÓRIO DE APOIO À ATIVIDADE PARLAMENTAR","codDocumento":7139658,"tipoDocumento":"Recibos/Outros","codTipoDocumento":1,"dataDocumento":"2020-12-17","numDocumento":"43172","valorDocumento":280.0,"urlDocumento":null,"nomeFornecedor":"CONDOMINIO DO EDIFÍCIO MONDRIAN TRADE CENTER","cnpjCpfFornecedor":"25703828000137","valorLiquido":280.0,"valorGlosa":0.0,"numRessarcimento":"","codLote":1738350,"parcela":0},{"ano":2021,"mes":1,"tipoDespesa":"MANUTENÇÃO DE ESCRITÓRIO DE APOIO À ATIVIDADE PARLAMENTAR","codDocumento":7139660,"tipoDocumento":"Recibos/Outros","codTipoDocumento":1,"dataDocumento":"2020-12-17","numDocumento":"43173","valorDocumento":280.0,"urlDocumento":null,"nomeFornecedor":"CONDOMINIO DO EDIFÍCIO MONDRIAN TRADE CENTER","cnpjCpfFornecedor":"25703828000137","valorLiquido":280.0,"valorGlosa":0.0,"numRessarcimento":"","codLote":1738350,"parcela":0},{"ano":2021,"mes":1,"tipoDespesa":"MANUTENÇÃO DE ESCRITÓRIO DE APOIO À ATIVIDADE PARLAMENTAR","codDocumento":7139664,"tipoDocumento":"Recibos/Outros","codTipoDocumento":1,"dataDocumento":"2020-12-17","numDocumento":"43197","valorDocumento":56.0,"urlDocumento":null,"nomeFornecedor":"CONDOMINIO DO EDIFÍCIO MONDRIAN TRADE CENTER","cnpjCpfFornecedor":"25703828000137","valorLiquido":56.0,"valorGlosa":0.0,"numRessarcimento":"","codLote":1738350,"parcela":0},{"ano":2021,"mes":2,"tipoDespesa":"MANUTENÇÃO DE ESCRITÓRIO DE APOIO À ATIVIDADE PARLAMENTAR","codDocumento":7153333,"tipoDocumento":"Recibos/Outros","codTipoDocumento":1,"dataDocumento":"2021-01-28","numDocumento":"43421","valorDocumento":280.0,"urlDocumento":null,"nomeFornecedor":"CONDOMINIO DO EDIFÍCIO MONDRIAN TRADE CENTER","cnpjCpfFornecedor":"25703828000137","valorLiquido":280.0,"valorGlosa":0.0,"numRessarcimento":"","codLote":1744968,"parcela":0},{"ano":2021,"mes":2,"tipoDespesa":"MANUTENÇÃO DE ESCRITÓRIO DE APOIO À ATIVIDADE PARLAMENTAR","codDocumento":7153339,"tipoDocumento":"Recibos/Outros","codTipoDocumento":1,"dataDocumento":"2021-01-28","numDocumento":"43422","valorDocumento":280.0,"urlDocumento":null,"nomeFornecedor":"CONDOMINIO DO EDIFÍCIO MONDRIAN TRADE CENTER","cnpjCpfFornecedor":"25703828000137","valorLiquido":280.0,"valorGlosa":0.0,"numRessarcimento":"","codLote":1744968,"parcela":0},{"ano":2021,"mes":2,"tipoDespesa":"MANUTENÇÃO DE ESCRITÓRIO DE APOIO À ATIVIDADE PARLAMENTAR","codDocumento":7153331,"tipoDocumento":"Recibos/Outros","codTipoDocumento":1,"dataDocumento":"2021-01-28","numDocumento":"43446","valorDocumento":56.0,"urlDocumento":null,"nomeFornecedor":"CONDOMINIO DO EDIFÍCIO MONDRIAN TRADE CENTER","cnpjCpfFornecedor":"25703828000137","valorLiquido":56.0,"valorGlosa":0.0,"numRessarcimento":"","codLote":1744968,"parcela":0},{"ano":2021,"mes":3,"tipoDespesa":"MANUTENÇÃO DE ESCRITÓRIO DE APOIO À ATIVIDADE PARLAMENTAR","codDocumento":7167829,"tipoDocumento":"Recibos/Outros","codTipoDocumento":1,"dataDocumento":"2021-02-25","numDocumento":"43668","valorDocumento":280.0,"urlDocumento":null,"nomeFornecedor":"CONDOMINIO DO EDIFÍCIO MONDRIAN TRADE CENTER","cnpjCpfFornecedor":"25703828000137","valorLiquido":280.0,"valorGlosa":0.0,"numRessarcimento":"","codLote":1752539,"parcela":0},{"ano":2021,"mes":3,"tipoDespesa":"MANUTENÇÃO DE ESCRITÓRIO DE APOIO À ATIVIDADE PARLAMENTAR","codDocumento":7167835,"tipoDocumento":"Recibos/Outros","codTipoDocumento":1,"dataDocumento":"2021-02-25","numDocumento":"43669","valorDocumento":280.0,"urlDocumento":null,"nomeFornecedor":"CONDOMINIO DO EDIFÍCIO MONDRIAN TRADE CENTER","cnpjCpfFornecedor":"25703828000137","valorLiquido":280.0,"valorGlosa":0.0,"numRessarcimento":"","codLote":1752539,"parcela":0},{"ano":2021,"mes":3,"tipoDespesa":"MANUTENÇÃO DE ESCRITÓRIO DE APOIO À ATIVIDADE PARLAMENTAR","codDocumento":7167845,"tipoDocumento":"Recibos/Outros","codTipoDocumento":1,"dataDocumento":"2021-02-25","numDocumento":"43693","valorDocumento":56.0,"urlDocumento":null,"nomeFornecedor":"CONDOMINIO DO EDIFÍCIO MONDRIAN TRADE CENTER","cnpjCpfFornecedor":"25703828000137","valorLiquido":56.0,"valorGlosa":0.0,"numRessarcimento":"","codLote":1752539,"parcela":0},{"ano":2021,"mes":4,"tipoDespesa":"MANUTENÇÃO DE ESCRITÓRIO DE APOIO À ATIVIDADE PARLAMENTAR","codDocumento":7178825,"tipoDocumento":"Recibos/Outros","codTipoDocumento":1,"dataDocumento":"2021-03-29","numDocumento":"43923","valorDocumento":280.0,"urlDocumento":null,"nomeFornecedor":"CONDOMINIO DO EDIFÍCIO MONDRIAN TRADE CENTER","cnpjCpfFornecedor":"25703828000137","valorLiquido":280.0,"valorGlosa":0.0,"numRessarcimento":"","codLote":1758155,"parcela":0},{"ano":2021,"mes":4,"tipoDespesa":"MANUTENÇÃO DE ESCRITÓRIO DE APOIO À ATIVIDADE PARLAMENTAR","codDocumento":7178827,"tipoDocumento":"Recibos/Outros","codTipoDocumento":1,"dataDocumento":"2021-03-29","numDocumento":"43924","valorDocumento":280.0,"urlDocumento":null,"nomeFornecedor":"CONDOMINIO DO EDIFÍCIO MONDRIAN TRADE CENTER","cnpjCpfFornecedor":"25703828000137","valorLiquido":280.0,"valorGlosa":0.0,"numRessarcimento":"","codLote":1758155,"parcela":0},{"ano":2021,"mes":4,"tipoDespesa":"MANUTENÇÃO DE ESCRITÓRIO DE APOIO À ATIVIDADE PARLAMENTAR","codDocumento":7178808,"tipoDocumento":"Recibos/Outros","codTipoDocumento":1,"dataDocumento":"2021-03-29","numDocumento":"43948","valorDocumento":56.0,"urlDocumento":null,"nomeFornecedor":"CONDOMINIO DO EDIFÍCIO MONDRIAN TRADE CENTER","cnpjCpfFornecedor":"25703828000137","valorLiquido":56.0,"valorGlosa":0.0,"numRessarcimento":"","codLote":1758155,"parcela":0},{"ano":2021,"mes":5,"tipoDespesa":"MANUTENÇÃO DE ESCRITÓRIO DE APOIO À ATIVIDADE PARLAMENTAR","codDocumento":7192292,"tipoDocumento":"Recibos/Outros","codTipoDocumento":1,"dataDocumento":"2021-04-27","numDocumento":"44170","valorDocumento":280.0,"urlDocumento":null,"nomeFornecedor":"CONDOMINIO DO EDIFÍCIO MONDRIAN TRADE CENTER","cnpjCpfFornecedor":"25703828000137","valorLiquido":280.0,"valorGlosa":0.0,"numRessarcimento":"","codLote":1764372,"parcela":0},{"ano":2021,"mes":5,"tipoDespesa":"MANUTENÇÃO DE ESCRITÓRIO DE APOIO À ATIVIDADE PARLAMENTAR","codDocumento":7192200,"tipoDocumento":"Recibos/Outros","codTipoDocumento":1,"dataDocumento":"2021-04-27","numDocumento":"44171","valorDocumento":280.0,"urlDocumento":null,"nomeFornecedor":"CONDOMINIO DO EDIFÍCIO MONDRIAN TRADE CENTER","cnpjCpfFornecedor":"25703828000137","valorLiquido":280.0,"valorGlosa":0.0,"numRessarcimento":"","codLote":1764371,"parcela":0},{"ano":2021,"mes":5,"tipoDespesa":"MANUTENÇÃO DE ESCRITÓRIO DE APOIO À ATIVIDADE PARLAMENTAR","codDocumento":7192196,"tipoDocumento":"Recibos/Outros","codTipoDocumento":1,"dataDocumento":"2021-04-27","numDocumento":"44195","valorDocumento":56.0,"urlDocumento":null,"nomeFornecedor":"CONDOMINIO DO EDIFÍCIO MONDRIAN TRADE CENTER","cnpjCpfFornecedor":"25703828000137","valorLiquido":56.0,"valorGlosa":0.0,"numRessarcimento":"","codLote":1764371,"parcela":0},{"ano":2021,"mes":6,"tipoDespesa":"MANUTENÇÃO DE ESCRITÓRIO DE APOIO À ATIVIDADE PARLAMENTAR","codDocumento":7221405,"tipoDocumento":"Recibos/Outros","codTipoDocumento":1,"dataDocumento":"2021-05-31","numDocumento":"44423","valorDocumento":280.0,"urlDocumento":null,"nomeFornecedor":"CONDOMINIO DO EDIFÍCIO MONDRIAN TRADE CENTER","cnpjCpfFornecedor":"25703828000137","valorLiquido":280.0,"valorGlosa":0.0,"numRessarcimento":"","codLote":1778713,"parcela":0},{"ano":2021,"mes":6,"tipoDespesa":"MANUTENÇÃO DE ESCRITÓRIO DE APOIO À ATIVIDADE PARLAMENTAR","codDocumento":7221408,"tipoDocumento":"Recibos/Outros","codTipoDocumento":1,"dataDocumento":"2021-05-27","numDocumento":"44424","valorDocumento":280.0,"urlDocumento":null,"nomeFornecedor":"CONDOMINIO DO EDIFÍCIO MONDRIAN TRADE CENTER","cnpjCpfFornecedor":"25703828000137","valorLiquido":280.0,"valorGlosa":0.0,"numRessarcimento":"","codLote":1778713,"parcela":0},{"ano":2021,"mes":6,"tipoDespesa":"MANUTENÇÃO DE ESCRITÓRIO DE APOIO À ATIVIDADE PARLAMENTAR","codDocumento":7221410,"tipoDocumento":"Recibos/Outros","codTipoDocumento":1,"dataDocumento":"2021-05-27","numDocumento":"44448","valorDocumento":56.0,"urlDocumento":null,"nomeFornecedor":"CONDOMINIO DO EDIFÍCIO MONDRIAN TRADE CENTER","cnpjCpfFornecedor":"25703828000137","valorLiquido":56.0,"valorGlosa":0.0,"numRessarcimento":"","codLote":1778713,"parcela":0},{"ano":2021,"mes":7,"tipoDespesa":"MANUTENÇÃO DE ESCRITÓRIO DE APOIO À ATIVIDADE PARLAMENTAR","codDocumento":7223837,"tipoDocumento":"Recibos/Outros","codTipoDocumento":1,"dataDocumento":"2021-06-29","numDocumento":"44670","valorDocumento":280.0,"urlDocumento":null,"nomeFornecedor":"CONDOMINIO DO EDIFÍCIO MONDRIAN TRADE CENTER","cnpjCpfFornecedor":"25703828000137","valorLiquido":280.0,"valorGlosa":0.0,"numRessarcimento":"","codLote":1779824,"parcela":0},{"ano":2021,"mes":7,"tipoDespesa":"MANUTENÇÃO DE ESCRITÓRIO DE APOIO À ATIVIDADE PARLAMENTAR","codDocumento":7223835,"tipoDocumento":"Recibos/Outros","codTipoDocumento":1,"dataDocumento":"2021-06-29","numDocumento":"44671","valorDocumento":280.0,"urlDocumento":null,"nomeFornecedor":"CONDOMINIO DO EDIFÍCIO MONDRIAN TRADE CENTER","cnpjCpfFornecedor":"25703828000137","valorLiquido":280.0,"valorGlosa":0.0,"numRessarcimento":"","codLote":1779824,"parcela":0},{"ano":2021,"mes":7,"tipoDespesa":"MANUTENÇÃO DE ESCRITÓRIO DE APOIO À ATIVIDADE PARLAMENTAR","codDocumento":7223840,"tipoDocumento":"Recibos/Outros","codTipoDocumento":1,"dataDocumento":"2021-06-29","numDocumento":"44695","valorDocumento":56.0,"urlDocumento":null,"nomeFornecedor":"CONDOMINIO DO EDIFÍCIO MONDRIAN TRADE CENTER","cnpjCpfFornecedor":"25703828000137","valorLiquido":56.0,"valorGlosa":0.0,"numRessarcimento":"","codLote":1779824,"parcela":0},{"ano":2021,"mes":8,"tipoDespesa":"MANUTENÇÃO DE ESCRITÓRIO DE APOIO À ATIVIDADE PARLAMENTAR","codDocumento":7251044,"tipoDocumento":"Recibos/Outros","codTipoDocumento":1,"dataDocumento":"2021-07-26","numDocumento":"44920","valorDocumento":280.0,"urlDocumento":null,"nomeFornecedor":"CONDOMINIO DO EDIFÍCIO MONDRIAN TRADE CENTER","cnpjCpfFornecedor":"25703828000137","valorLiquido":280.0,"valorGlosa":0.0,"numRessarcimento":"","codLote":1792149,"parcela":0},{"ano":2021,"mes":8,"tipoDespesa":"MANUTENÇÃO DE ESCRITÓRIO DE APOIO À ATIVIDADE PARLAMENTAR","codDocumento":7251047,"tipoDocumento":"Recibos/Outros","codTipoDocumento":1,"dataDocumento":"2021-07-26","numDocumento":"44921","valorDocumento":280.0,"urlDocumento":null,"nomeFornecedor":"CONDOMINIO DO EDIFÍCIO MONDRIAN TRADE CENTER","cnpjCpfFornecedor":"25703828000137","valorLiquido":280.0,"valorGlosa":0.0,"numRessarcimento":"","codLote":1792149,"parcela":0},{"ano":2021,"mes":8,"tipoDespesa":"MANUTENÇÃO DE ESCRITÓRIO DE APOIO À ATIVIDADE PARLAMENTAR","codDocumento":7251036,"tipoDocumento":"Recibos/Outros","codTipoDocumento":1,"dataDocumento":"2021-07-26","numDocumento":"44945","valorDocumento":56.0,"urlDocumento":null,"nomeFornecedor":"CONDOMINIO DO EDIFÍCIO MONDRIAN TRADE CENTER","cnpjCpfFornecedor":"25703828000137","valorLiquido":56.0,"valorGlosa":0.0,"numRessarcimento":"","codLote":1792149,"parcela":0},{"ano":2021,"mes":9,"tipoDespesa":"MANUTENÇÃO DE ESCRITÓRIO DE APOIO À ATIVIDADE PARLAMENTAR","codDocumento":7257434,"tipoDocumento":"Recibos/Outros","codTipoDocumento":1,"dataDocumento":"2021-08-26","numDocumento":"45179","valorDocumento":280.0,"urlDocumento":null,"nomeFornecedor":"CONDOMINIO DO EDIFÍCIO MONDRIAN TRADE CENTER","cnpjCpfFornecedor":"25703828000137","valorLiquido":280.0,"valorGlosa":0.0,"numRessarcimento":"","codLote":1795017,"parcela":0},{"ano":2021,"mes":9,"tipoDespesa":"MANUTENÇÃO DE ESCRITÓRIO DE APOIO À ATIVIDADE PARLAMENTAR","codDocumento":7257431,"tipoDocumento":"Recibos/Outros","codTipoDocumento":1,"dataDocumento":"2021-08-26","numDocumento":"45180","valorDocumento":280.0,"urlDocumento":null,"nomeFornecedor":"CONDOMINIO DO EDIFÍCIO MONDRIAN TRADE CENTER","cnpjCpfFornecedor":"25703828000137","valorLiquido":280.0,"valorGlosa":0.0,"numRessarcimento":"","codLote":1795017,"parcela":0},{"ano":2021,"mes":9,"tipoDespesa":"MANUTENÇÃO DE ESCRITÓRIO DE APOIO À ATIVIDADE PARLAMENTAR","codDocumento":7257438,"tipoDocumento":"Recibos/Outros","codTipoDocumento":1,"dataDocumento":"2021-08-26","numDocumento":"45204","valorDocumento":56.0,"urlDocumento":null,"nomeFornecedor":"CONDOMINIO DO EDIFÍCIO MONDRIAN TRADE CENTER","cnpjCpfFornecedor":"25703828000137","valorLiquido":56.0,"valorGlosa":0.0,"numRessarcimento":"","codLote":1795017,"parcela":0},{"ano":2021,"mes":10,"tipoDespesa":"MANUTENÇÃO DE ESCRITÓRIO DE APOIO À ATIVIDADE PARLAMENTAR","codDocumento":7280374,"tipoDocumento":"Recibos/Outros","codTipoDocumento":1,"dataDocumento":"2021-09-29","numDocumento":"45426","valorDocumento":280.0,"urlDocumento":null,"nomeFornecedor":"CONDOMINIO DO EDIFÍCIO MONDRIAN TRADE CENTER","cnpjCpfFornecedor":"25703828000137","valorLiquido":280.0,"valorGlosa":0.0,"numRessarcimento":"","codLote":1805371,"parcela":0},{"ano":2021,"mes":10,"tipoDespesa":"MANUTENÇÃO DE ESCRITÓRIO DE APOIO À ATIVIDADE PARLAMENTAR","codDocumento":7280364,"tipoDocumento":"Recibos/Outros","codTipoDocumento":1,"dataDocumento":"2021-10-29","numDocumento":"45427","valorDocumento":280.0,"urlDocumento":null,"nomeFornecedor":"CONDOMINIO DO EDIFÍCIO MONDRIAN TRADE CENTER","cnpjCpfFornecedor":"25703828000137","valorLiquido":280.0,"valorGlosa":0.0,"numRessarcimento":"","codLote":1805371,"parcela":0},{"ano":2021,"mes":10,"tipoDespesa":"MANUTENÇÃO DE ESCRITÓRIO DE APOIO À ATIVIDADE PARLAMENTAR","codDocumento":7280379,"tipoDocumento":"Recibos/Outros","codTipoDocumento":1,"dataDocumento":"2021-09-29","numDocumento":"45451","valorDocumento":56.0,"urlDocumento":null,"nomeFornecedor":"CONDOMINIO DO EDIFÍCIO MONDRIAN TRADE CENTER","cnpjCpfFornecedor":"25703828000137","valorLiquido":56.0,"valorGlosa":0.0,"numRessarcimento":"","codLote":1805371,"parcela":0},{"ano":2021,"mes":11,"tipoDespesa":"MANUTENÇÃO DE ESCRITÓRIO DE APOIO À ATIVIDADE PARLAMENTAR","codDocumento":7298755,"tipoDocumento":"Recibos/Outros","codTipoDocumento":1,"dataDocumento":"2021-10-28","numDocumento":"45675","valorDocumento":300.0,"urlDocumento":null,"nomeFornecedor":"CONDOMINIO DO EDIFÍCIO MONDRIAN TRADE CENTER","cnpjCpfFornecedor":"25703828000137","valorLiquido":300.0,"valorGlosa":0.0,"numRessarcimento":"","codLote":1813370,"parcela":0},{"ano":2021,"mes":11,"tipoDespesa":"MANUTENÇÃO DE ESCRITÓRIO DE APOIO À ATIVIDADE PARLAMENTAR","codDocumento":7298749,"tipoDocumento":"Recibos/Outros","codTipoDocumento":1,"dataDocumento":"2021-10-28","numDocumento":"45676","valorDocumento":300.0,"urlDocumento":null,"nomeFornecedor":"CONDOMINIO DO EDIFÍCIO MONDRIAN TRADE CENTER","cnpjCpfFornecedor":"25703828000137","valorLiquido":300.0,"valorGlosa":0.0,"numRessarcimento":"","codLote":1813370,"parcela":0},{"ano":2021,"mes":11,"tipoDespesa":"MANUTENÇÃO DE ESCRITÓRIO DE APOIO À ATIVIDADE PARLAMENTAR","codDocumento":7298743,"tipoDocumento":"Recibos/Outros","codTipoDocumento":1,"dataDocumento":"2021-10-28","numDocumento":"45700","valorDocumento":60.0,"urlDocumento":null,"nomeFornecedor":"CONDOMINIO DO EDIFÍCIO MONDRIAN TRADE CENTER","cnpjCpfFornecedor":"25703828000137","valorLiquido":60.0,"valorGlosa":0.0,"numRessarcimento":"","codLote":1813370,"parcela":0},{"ano":2021,"mes":1,"tipoDespesa":"MANUTENÇÃO DE ESCRITÓRIO DE APOIO À ATIVIDADE PARLAMENTAR","codDocumento":7144171,"tipoDocumento":"Nota Fiscal","codTipoDocumento":0,"dataDocumento":"2021-01-04","numDocumento":"1991","valorDocumento":265.9,"urlDocumento":null,"nomeFornecedor":"FORTIL LTDA","cnpjCpfFornecedor":"20154795000108","valorLiquido":265.9,"valorGlosa":0.0,"numRessarcimento":"","codLote":1740399,"parcela":0},{"ano":2021,"mes":5,"tipoDespesa":"MANUTENÇÃO DE ESCRITÓRIO DE APOIO À ATIVIDADE PARLAMENTAR","codDocumento":7205685,"tipoDocumento":"Nota Fiscal","codTipoDocumento":0,"dataDocumento":"2021-05-03","numDocumento":"3116","valorDocumento":45.0,"urlDocumento":null,"nomeFornecedor":"FORTIL LTDA","cnpjCpfFornecedor":"20154795000108","valorLiquido":45.0,"valorGlosa":0.0,"numRessarcimento":"","codLote":1770674,"parcela":0},{"ano":2021,"mes":9,"tipoDespesa":"MANUTENÇÃO DE ESCRITÓRIO DE APOIO À ATIVIDADE PARLAMENTAR","codDocumento":7251193,"tipoDocumento":"Nota Fiscal","codTipoDocumento":0,"dataDocumento":"2021-09-01","numDocumento":"4194","valorDocumento":156.96,"urlDocumento":null,"nomeFornecedor":"FORTIL LTDA","cnpjCpfFornecedor":"20154795000108","valorLiquido":156.96,"valorGlosa":0.0,"numRessarcimento":"","codLote":1792154,"parcela":0},{"ano":2021,"mes":1,"tipoDespesa":"MANUTENÇÃO DE ESCRITÓRIO DE APOIO À ATIVIDADE PARLAMENTAR","codDocumento":7162437,"tipoDocumento":"Recibos/Outros","codTipoDocumento":1,"dataDocumento":"2021-02-01","numDocumento":"53694","valorDocumento":1045.93,"urlDocumento":null,"nomeFornecedor":"PALUMA IMOVEIS EIRELI","cnpjCpfFornecedor":"05845088000166","valorLiquido":1045.93,"valorGlosa":0.0,"numRessarcimento":"","codLote":1749401,"parcela":0},{"ano":2021,"mes":2,"tipoDespesa":"MANUTENÇÃO DE ESCRITÓRIO DE APOIO À ATIVIDADE PARLAMENTAR","codDocumento":7167819,"tipoDocumento":"Recibos/Outros","codTipoDocumento":1,"dataDocumento":"2021-03-02","numDocumento":"57427","valorDocumento":1045.93,"urlDocumento":null,"nomeFornecedor":"PALUMA IMOVEIS EIRELI","cnpjCpfFornecedor":"05845088000166","valorLiquido":1045.93,"valorGlosa":0.0,"numRessarcimento":"","codLote":1752535,"parcela":0},{"ano":2021,"mes":3,"tipoDespesa":"MANUTENÇÃO DE ESCRITÓRIO DE APOIO À ATIVIDADE PARLAMENTAR","codDocumento":7178803,"tipoDocumento":"Recibos/Outros","codTipoDocumento":1,"dataDocumento":"2021-03-31","numDocumento":"60788","valorDocumento":1096.35,"urlDocumento":null,"nomeFornecedor":"PALUMA IMOVEIS EIRELI","cnpjCpfFornecedor":"05845088000166","valorLiquido":1096.35,"valorGlosa":0.0,"numRessarcimento":"","codLote":1758154,"parcela":0},{"ano":2021,"mes":4,"tipoDespesa":"MANUTENÇÃO DE ESCRITÓRIO DE APOIO À ATIVIDADE PARLAMENTAR","codDocumento":7205676,"tipoDocumento":"Recibos/Outros","codTipoDocumento":1,"dataDocumento":"2021-05-03","numDocumento":"64476","valorDocumento":1106.35,"urlDocumento":null,"nomeFornecedor":"PALUMA IMOVEIS EIRELI","cnpjCpfFornecedor":"05845088000166","valorLiquido":1106.35,"valorGlosa":0.0,"numRessarcimento":"","codLote":1770656,"parcela":0},{"ano":2021,"mes":5,"tipoDespesa":"MANUTENÇÃO DE ESCRITÓRIO DE APOIO À ATIVIDADE PARLAMENTAR","codDocumento":7221394,"tipoDocumento":"Recibos/Outros","codTipoDocumento":1,"dataDocumento":"2021-05-31","numDocumento":"67920","valorDocumento":1106.35,"urlDocumento":null,"nomeFornecedor":"PALUMA IMOVEIS EIRELI","cnpjCpfFornecedor":"05845088000166","valorLiquido":1106.35,"valorGlosa":0.0,"numRessarcimento":"","codLote":1778714,"parcela":0},{"ano":2021,"mes":6,"tipoDespesa":"MANUTENÇÃO DE ESCRITÓRIO DE APOIO À ATIVIDADE PARLAMENTAR","codDocumento":7223801,"tipoDocumento":"Recibos/Outros","codTipoDocumento":1,"dataDocumento":"2021-07-08","numDocumento":"72549","valorDocumento":1106.35,"urlDocumento":null,"nomeFornecedor":"PALUMA IMOVEIS EIRELI","cnpjCpfFornecedor":"05845088000166","valorLiquido":1106.35,"valorGlosa":0.0,"numRessarcimento":"","codLote":1779823,"parcela":0},{"ano":2021,"mes":7,"tipoDespesa":"MANUTENÇÃO DE ESCRITÓRIO DE APOIO À ATIVIDADE PARLAMENTAR","codDocumento":7251021,"tipoDocumento":"Recibos/Outros","codTipoDocumento":1,"dataDocumento":"2021-07-31","numDocumento":"76384","valorDocumento":1180.51,"urlDocumento":null,"nomeFornecedor":"PALUMA IMOVEIS EIRELI","cnpjCpfFornecedor":"05845088000166","valorLiquido":1180.51,"valorGlosa":0.0,"numRessarcimento":"","codLote":1792148,"parcela":0},{"ano":2021,"mes":8,"tipoDespesa":"MANUTENÇÃO DE ESCRITÓRIO DE APOIO À ATIVIDADE PARLAMENTAR","codDocumento":7274000,"tipoDocumento":"Recibos/Outros","codTipoDocumento":1,"dataDocumento":"2021-08-31","numDocumento":"80044","valorDocumento":1180.51,"urlDocumento":null,"nomeFornecedor":"PALUMA IMOVEIS EIRELI","cnpjCpfFornecedor":"05845088000166","valorLiquido":1180.51,"valorGlosa":0.0,"numRessarcimento":"","codLote":1802372,"parcela":0},{"ano":2021,"mes":9,"tipoDespesa":"MANUTENÇÃO DE ESCRITÓRIO DE APOIO À ATIVIDADE PARLAMENTAR","codDocumento":7280311,"tipoDocumento":"Recibos/Outros","codTipoDocumento":1,"dataDocumento":"2021-10-01","numDocumento":"83678","valorDocumento":1180.51,"urlDocumento":null,"nomeFornecedor":"PALUMA IMOVEIS EIRELI","cnpjCpfFornecedor":"05845088000166","valorLiquido":1180.51,"valorGlosa":0.0,"numRessarcimento":"","codLote":1805366,"parcela":0},{"ano":2021,"mes":10,"tipoDespesa":"MANUTENÇÃO DE ESCRITÓRIO DE APOIO À ATIVIDADE PARLAMENTAR","codDocumento":7298722,"tipoDocumento":"Recibos/Outros","codTipoDocumento":1,"dataDocumento":"2021-11-01","numDocumento":"87029","valorDocumento":1106.35,"urlDocumento":null,"nomeFornecedor":"PALUMA IMOVEIS EIRELI","cnpjCpfFornecedor":"05845088000166","valorLiquido":1106.35,"valorGlosa":0.0,"numRessarcimento":"","codLote":1813366,"parcela":0},{"ano":2021,"mes":12,"tipoDespesa":"MANUTENÇÃO DE ESCRITÓRIO DE APOIO À ATIVIDADE PARLAMENTAR","codDocumento":7329001,"tipoDocumento":"Recibos/Outros","codTipoDocumento":1,"dataDocumento":"2022-01-04","numDocumento":"95108","valorDocumento":1106.35,"urlDocumento":"https://www.camara.leg.br/cota-parlamentar/documentos/publ/2235/2022/7329001.pdf","nomeFornecedor":"PALUMA IMOVEIS EIRELI","cnpjCpfFornecedor":"05845088000166","valorLiquido":1106.35,"valorGlosa":0.0,"numRessarcimento":"","codLote":1828434,"parcela":0},{"ano":2021,"mes":5,"tipoDespesa":"MANUTENÇÃO DE ESCRITÓRIO DE APOIO À ATIVIDADE PARLAMENTAR","codDocumento":7192325,"tipoDocumento":"Nota Fiscal Eletrônica","codTipoDocumento":4,"dataDocumento":"2021-05-12","numDocumento":"49373","valorDocumento":235.9,"urlDocumento":"http://www.camara.leg.br/cota-parlamentar/nota-fiscal-eletronica?ideDocumentoFiscal=7192325","nomeFornecedor":"PAPELARIA E LIVRARIA J A LTDA","cnpjCpfFornecedor":"31944125000101","valorLiquido":235.9,"valorGlosa":0.0,"numRessarcimento":"","codLote":1764380,"parcela":0}],"links":[{"rel":"self","href":"https://dadosabertos.camara.leg.br/api/v2/deputados/160758/despesas?ano=2021&itens=10000"},{"rel":"next","href":"https://dadosabertos.camara.leg.br/api/v2/deputados/160758/despesas?ano=2021&pagina=2&itens=100"},{"rel":"first","href":"https://dadosabertos.camara.leg.br/api/v2/deputados/160758/despesas?ano=2021&pagina=1&itens=100"},{"rel":"last","href":"https://dadosabertos.camara.leg.br/api/v2/deputados/160758/despesas?ano=2021&pagina=6&itens=100"}]}
