{"dados":[{"ano":2021,"mes":1,"tipoDespesa":"MANUTENÇÃO DE ESCRITÓRIO DE APOIO À ATIVIDADE PARLAMENTAR","codDocumento":7159238,"tipoDocumento":"Nota Fiscal","codTipoDocumento":0,"dataDocumento":"2021-01-19","numDocumento":"10433757","valorDocumento":46.0,"urlDocumento":"https://www.camara.leg.br/cota-parlamentar/documentos/publ/2995/2021/7159238.pdf","nomeFornecedor":"BRK Ambiental","cnpjCpfFornecedor":"00585900000148","valorLiquido":46.0,"valorGlosa":0.0,"numRessarcimento":"","codLote":1747798,"parcela":0},{"ano":2021,"mes":2,"tipoDespesa":"MANUTENÇÃO DE ESCRITÓRIO DE APOIO À ATIVIDADE PARLAMENTAR","codDocumento":7169437,"tipoDocumento":"Nota Fiscal","codTipoDocumento":0,"dataDocumento":"2021-02-18","numDocumento":"1043757","valorDocumento":46.0,"urlDocumento":"https://www.camara.leg.br/cota-parlamentar/documentos/publ/2995/2021/7169437.pdf","nomeFornecedor":"BRK Ambiental","cnpjCpfFornecedor":"00585900000148","valorLiquido":46.0,"valorGlosa":0.0,"numRessarcimento":"","codLote":1753595,"parcela":0},{"ano":2021,"mes":3,"tipoDespesa":"MANUTENÇÃO DE ESCRITÓRIO DE APOIO À ATIVIDADE PARLAMENTAR","codDocumento":7181893,"tipoDocumento":"Nota Fiscal","codTipoDocumento":0,"dataDocumento":"2021-04-12","numDocumento":"1043757","valorDocumento":46.0,"urlDocumento":"https://www.camara.leg.br/cota-parlamentar/documentos/publ/2995/2021/7181893.pdf","nomeFornecedor":"BRK Ambiental","cnpjCpfFornecedor":"00585900000148","valorLiquido":46.0,"valorGlosa":0.0,"numRessarcimento":"","codLote":1759597,"parcela":0},{"ano":2021,"mes":4,"tipoDespesa":"MANUTENÇÃO DE ESCRITÓRIO DE APOIO À ATIVIDADE PARLAMENTAR","codDocumento":7202540,"tipoDocumento":"Nota Fiscal","codTipoDocumento":0,"dataDocumento":"2021-05-11","numDocumento":"1043757","valorDocumento":46.0,"urlDocumento":"https://www.camara.leg.br/cota-parlamentar/documentos/publ/2995/2021/7202540.pdf","nomeFornecedor":"BRK Ambiental","cnpjCpfFornecedor":"00585900000148","valorLiquido":46.0,"valorGlosa":0.0,"numRessarcimento":"","codLote":1769158,"parcela":0},{"ano":2021,"mes":5,"tipoDespesa":"MANUTENÇÃO DE ESCRITÓRIO DE APOIO À ATIVIDADE PARLAMENTAR","codDocumento":7214755,"tipoDocumento":"Nota Fiscal","codTipoDocumento":0,"dataDocumento":"2021-05-19","numDocumento":"1043757","valorDocumento":46.0,"urlDocumento":"https://www.camara.leg.br/cota-parlamentar/documentos/publ/2995/2021/7214755.pdf","nomeFornecedor":"BRK Ambiental","cnpjCpfFornecedor":"00585900000148","valorLiquido":46.0,"valorGlosa":0.0,"numRessarcimento":"","codLote":1776677,"parcela":0},{"ano":2021,"mes":7,"tipoDespesa":"MANUTENÇÃO DE ESCRITÓRIO DE APOIO À ATIVIDADE PARLAMENTAR","codDocumento":7255723,"tipoDocumento":"Nota Fiscal","codTipoDocumento":0,"dataDocumento":"2021-07-22","numDocumento":"1043757","valorDocumento":46.0,"urlDocumento":"https://www.camara.leg.br/cota-parlamentar/documentos/publ/2995/2021/7255723.pdf","nomeFornecedor":"BRK Ambiental","cnpjCpfFornecedor":"00585900000148","valorLiquido":46.0,"valorGlosa":0.0,"numRessarcimento":"","codLote":1795025,"parcela":0},{"ano":2021,"mes":9,"tipoDespesa":"MANUTENÇÃO DE ESCRITÓRIO DE APOIO À ATIVIDADE PARLAMENTAR","codDocumento":7285897,"tipoDocumento":"Nota Fiscal","codTipoDocumento":0,"dataDocumento":"2021-09-22","numDocumento":"1043757","valorDocumento":51.6,"urlDocumento":"https://www.camara.leg.br/cota-parlamentar/documentos/publ/2995/2021/7285897.pdf","nomeFornecedor":"BRK Ambiental","cnpjCpfFornecedor":"00585900000148","valorLiquido":51.6,"valorGlosa":0.0,"numRessarcimento":"","codLote":1807771,"parcela":0},{"ano":2021,"mes":10,"tipoDespesa":"MANUTENÇÃO DE ESCRITÓRIO DE APOIO À ATIVIDADE PARLAMENTAR","codDocumento":7289559,"tipoDocumento":"Nota Fiscal","codTipoDocumento":0,"dataDocumento":"2021-10-22","numDocumento":"1043757","valorDocumento":51.6,"urlDocumento":"https://www.camara.leg.br/cota-parlamentar/documentos/publ/2995/2021/7289559.pdf","nomeFornecedor":"BRK Ambiental","cnpjCpfFornecedor":"00585900000148","valorLiquido":51.6,"valorGlosa":0.0,"numRessarcimento":"","codLote":1809238,"parcela":0},{"ano":2021,"mes":12,"tipoDespesa":"MANUTENÇÃO DE ESCRITÓRIO DE APOIO À ATIVIDADE PARLAMENTAR","codDocumento":7320684,"tipoDocumento":"Nota Fiscal","codTipoDocumento":0,"dataDocumento":"2022-01-11","numDocumento":"1043757","valorDocumento":51.6,"urlDocumento":"https://www.camara.leg.br/cota-parlamentar/documentos/publ/2995/2022/7320684.pdf","nomeFornecedor":"BRK Ambiental","cnpjCpfFornecedor":"00585900000148","valorLiquido":51.6,"valorGlosa":0.0,"numRessarcimento":"","codLote":1823762,"parcela":0},{"ano":2021,"mes":2,"tipoDespesa":"MANUTENÇÃO DE ESCRITÓRIO DE APOIO À ATIVIDADE PARLAMENTAR","codDocumento":7169436,"tipoDocumento":"Nota Fiscal","codTipoDocumento":0,"dataDocumento":"2021-02-18","numDocumento":"27629284","valorDocumento":46.0,"urlDocumento":"https://www.camara.leg.br/cota-parlamentar/documentos/publ/2995/2021/7169436.pdf","nomeFornecedor":"BRK Ambiental","cnpjCpfFornecedor":"00585900000148","valorLiquido":46.0,"valorGlosa":0.0,"numRessarcimento":"","codLote":1753332,"parcela":0},{"ano":2021,"mes":6,"tipoDespesa":"MANUTENÇÃO DE ESCRITÓRIO DE APOIO À ATIVIDADE PARLAMENTAR","codDocumento":7226059,"tipoDocumento":"Nota Fiscal","codTipoDocumento":0,"dataDocumento":"2021-06-21","numDocumento":"28059354","valorDocumento":46.0,"urlDocumento":"https://www.camara.leg.br/cota-parlamentar/documentos/publ/2995/2021/7226059.pdf","nomeFornecedor":"BRK Ambiental","cnpjCpfFornecedor":"00585900000148","valorLiquido":46.0,"valorGlosa":0.0,"numRessarcimento":"","codLote":1780830,"parcela":0},{"ano":2021,"mes":11,"tipoDespesa":"MANUTENÇÃO DE ESCRITÓRIO DE APOIO À ATIVIDADE PARLAMENTAR","codDocumento":7310945,"tipoDocumento":"Nota Fiscal","codTipoDocumento":0,"dataDocumento":"2021-11-23","numDocumento":"28605711","valorDocumento":51.6,"urlDocumento":"https://www.camara.leg.br/cota-parlamentar/documentos/publ/2995/2021/7310945.pdf","nomeFornecedor":"BRK Ambiental","cnpjCpfFornecedor":"00585900000148","valorLiquido":51.6,"valorGlosa":0.0,"numRessarcimento":"","codLote":1819059,"parcela":0},{"ano":2021,"mes":1,"tipoDespesa":"MANUTENÇÃO DE ESCRITÓRIO DE APOIO À ATIVIDADE PARLAMENTAR","codDocumento":7159320,"tipoDocumento":"Nota Fiscal","codTipoDocumento":0,"dataDocumento":"2021-01-19","numDocumento":"65536","valorDocumento":46.0,"urlDocumento":"https://www.camara.leg.br/cota-parlamentar/documentos/publ/2995/2021/7159320.pdf","nomeFornecedor":"BRK Ambiental","cnpjCpfFornecedor":"00585900000148","valorLiquido":46.0,"valorGlosa":0.0,"numRessarcimento":"","codLote":1747785,"parcela":0},{"ano":2021,"mes":3,"tipoDespesa":"MANUTENÇÃO DE ESCRITÓRIO DE APOIO À ATIVIDADE PARLAMENTAR","codDocumento":7181892,"tipoDocumento":"Nota Fiscal","codTipoDocumento":0,"dataDocumento":"2021-03-19","numDocumento":"65536","valorDocumento":46.0,"urlDocumento":"https://www.camara.leg.br/cota-parlamentar/documentos/publ/2995/2021/7181892.pdf","nomeFornecedor":"BRK Ambiental","cnpjCpfFornecedor":"00585900000148","valorLiquido":46.0,"valorGlosa":0.0,"numRessarcimento":"","codLote":1759591,"parcela":0},{"ano":2021,"mes":5,"tipoDespesa":"MANUTENÇÃO DE ESCRITÓRIO DE APOIO À ATIVIDADE PARLAMENTAR","codDocumento":7214752,"tipoDocumento":"Nota Fiscal","codTipoDocumento":0,"dataDocumento":"2021-05-19","numDocumento":"65536","valorDocumento":46.0,"urlDocumento":"https://www.camara.leg.br/cota-parlamentar/documentos/publ/2995/2021/7214752.pdf","nomeFornecedor":"BRK Ambiental","cnpjCpfFornecedor":"00585900000148","valorLiquido":46.0,"valorGlosa":0.0,"numRessarcimento":"","codLote":1775839,"parcela":0},{"ano":2021,"mes":6,"tipoDespesa":"MANUTENÇÃO DE ESCRITÓRIO DE APOIO À ATIVIDADE PARLAMENTAR","codDocumento":7255701,"tipoDocumento":"Nota Fiscal","codTipoDocumento":0,"dataDocumento":"2021-06-21","numDocumento":"65536","valorDocumento":46.0,"urlDocumento":"https://www.camara.leg.br/cota-parlamentar/documentos/publ/2995/2021/7255701.pdf","nomeFornecedor":"BRK Ambiental","cnpjCpfFornecedor":"00585900000148","valorLiquido":46.0,"valorGlosa":0.0,"numRessarcimento":"","codLote":1794258,"parcela":0},{"ano":2021,"mes":7,"tipoDespesa":"MANUTENÇÃO DE ESCRITÓRIO DE APOIO À ATIVIDADE PARLAMENTAR","codDocumento":7255703,"tipoDocumento":"Nota Fiscal","codTipoDocumento":0,"dataDocumento":"2021-07-22","numDocumento":"65536","valorDocumento":46.0,"urlDocumento":"https://www.camara.leg.br/cota-parlamentar/documentos/publ/2995/2021/7255703.pdf","nomeFornecedor":"BRK Ambiental","cnpjCpfFornecedor":"00585900000148","valorLiquido":46.0,"valorGlosa":0.0,"numRessarcimento":"","codLote":1794266,"parcela":0},{"ano":2021,"mes":8,"tipoDespesa":"MANUTENÇÃO DE ESCRITÓRIO DE APOIO À ATIVIDADE PARLAMENTAR","codDocumento":7255707,"tipoDocumento":"Nota Fiscal","codTipoDocumento":0,"dataDocumento":"2021-08-20","numDocumento":"65536","valorDocumento":51.6,"urlDocumento":"https://www.camara.leg.br/cota-parlamentar/documentos/publ/2995/2021/7255707.pdf","nomeFornecedor":"BRK Ambiental","cnpjCpfFornecedor":"00585900000148","valorLiquido":51.6,"valorGlosa":0.0,"numRessarcimento":"","codLote":1795019,"parcela":0},{"ano":2021,"mes":9,"tipoDespesa":"MANUTENÇÃO DE ESCRITÓRIO DE APOIO À ATIVIDADE PARLAMENTAR","codDocumento":7273920,"tipoDocumento":"Nota Fiscal","codTipoDocumento":0,"dataDocumento":"2021-09-22","numDocumento":"65536","valorDocumento":51.6,"urlDocumento":"https://www.camara.leg.br/cota-parlamentar/documentos/publ/2995/2021/7273920.pdf","nomeFornecedor":"BRK Ambiental","cnpjCpfFornecedor":"00585900000148","valorLiquido":51.6,"valorGlosa":0.0,"numRessarcimento":"","codLote":1802332,"parcela":0},{"ano":2021,"mes":11,"tipoDespesa":"MANUTENÇÃO DE ESCRITÓRIO DE APOIO À ATIVIDADE PARLAMENTAR","codDocumento":7314799,"tipoDocumento":"Nota Fiscal","codTipoDocumento":0,"dataDocumento":"2021-11-23","numDocumento":"65536","valorDocumento":51.6,"urlDocumento":"https://www.camara.leg.br/cota-parlamentar/documentos/publ/2995/2022/7314799.pdf","nomeFornecedor":"BRK Ambiental","cnpjCpfFornecedor":"00585900000148","valorLiquido":51.6,"valorGlosa":0.0,"numRessarcimento":"","codLote":1820953,"parcela":0},{"ano":2021,"mes":12,"tipoDespesa":"MANUTENÇÃO DE ESCRITÓRIO DE APOIO À ATIVIDADE PARLAMENTAR","codDocumento":7315808,"tipoDocumento":"Nota Fiscal","codTipoDocumento":0,"dataDocumento":"2022-01-11","numDocumento":"65536","valorDocumento":51.6,"urlDocumento":"https://www.camara.leg.br/cota-parlamentar/documentos/publ/2995/2022/7315808.pdf","nomeFornecedor":"BRK Ambiental","cnpjCpfFornecedor":"00585900000148","valorLiquido":51.6,"valorGlosa":0.0,"numRessarcimento":"","codLote":1821406,"parcela":0},{"ano":2021,"mes":4,"tipoDespesa":"MANUTENÇÃO DE ESCRITÓRIO DE APOIO À ATIVIDADE PARLAMENTAR","codDocumento":7199521,"tipoDocumento":"Nota Fiscal","codTipoDocumento":0,"dataDocumento":"2021-04-19","numDocumento":"65536/042021","valorDocumento":46.0,"urlDocumento":"https://www.camara.leg.br/cota-parlamentar/documentos/publ/2995/2021/7199521.pdf","nomeFornecedor":"BRK Ambiental","cnpjCpfFornecedor":"00585900000148","valorLiquido":46.0,"valorGlosa":0.0,"numRessarcimento":"","codLote":1767686,"parcela":0},{"ano":2021,"mes":7,"tipoDespesa":"MANUTENÇÃO DE ESCRITÓRIO DE APOIO À ATIVIDADE PARLAMENTAR","codDocumento":7245711,"tipoDocumento":"Nota Fiscal","codTipoDocumento":0,"dataDocumento":"2021-07-21","numDocumento":"0000470689","valorDocumento":368.96,"urlDocumento":"https://www.camara.leg.br/cota-parlamentar/documentos/publ/2995/2021/7245711.pdf","nomeFornecedor":"CLARO NXT TELECOMUNICAÇÕES S.A.","cnpjCpfFornecedor":"66970229000167","valorLiquido":362.3,"valorGlosa":6.66,"numRessarcimento":"","codLote":1789533,"parcela":0},{"ano":2021,"mes":8,"tipoDespesa":"MANUTENÇÃO DE ESCRITÓRIO DE APOIO À ATIVIDADE PARLAMENTAR","codDocumento":7258251,"tipoDocumento":"Nota Fiscal","codTipoDocumento":0,"dataDocumento":"2021-08-20","numDocumento":"0005013096","valorDocumento":369.6,"urlDocumento":"https://www.camara.leg.br/cota-parlamentar/documentos/publ/2995/2021/7258251.pdf","nomeFornecedor":"CLARO NXT TELECOMUNICAÇÕES S.A.","cnpjCpfFornecedor":"66970229000167","valorLiquido":362.3,"valorGlosa":7.3,"numRessarcimento":"","codLote":1795357,"parcela":0},{"ano":2021,"mes":9,"tipoDespesa":"MANUTENÇÃO DE ESCRITÓRIO DE APOIO À ATIVIDADE PARLAMENTAR","codDocumento":7272142,"tipoDocumento":"Nota Fiscal","codTipoDocumento":0,"dataDocumento":"2021-09-15","numDocumento":"0009193108","valorDocumento":381.32,"urlDocumento":"https://www.camara.leg.br/cota-parlamentar/documentos/publ/2995/2021/7272142.pdf","nomeFornecedor":"CLARO NXT TELECOMUNICAÇÕES S.A.","cnpjCpfFornecedor":"66970229000167","valorLiquido":374.02,"valorGlosa":7.3,"numRessarcimento":"","codLote":1801528,"parcela":0},{"ano":2021,"mes":10,"tipoDespesa":"MANUTENÇÃO DE ESCRITÓRIO DE APOIO À ATIVIDADE PARLAMENTAR","codDocumento":7285914,"tipoDocumento":"Nota Fiscal","codTipoDocumento":0,"dataDocumento":"2021-10-22","numDocumento":"0013944812","valorDocumento":381.0,"urlDocumento":"https://www.camara.leg.br/cota-parlamentar/documentos/publ/2995/2021/7285914.pdf","nomeFornecedor":"CLARO NXT TELECOMUNICAÇÕES S.A.","cnpjCpfFornecedor":"66970229000167","valorLiquido":373.99,"valorGlosa":7.01,"numRessarcimento":"","codLote":1807767,"parcela":0},{"ano":2021,"mes":11,"tipoDespesa":"MANUTENÇÃO DE ESCRITÓRIO DE APOIO À ATIVIDADE PARLAMENTAR","codDocumento":7302356,"tipoDocumento":"Nota Fiscal","codTipoDocumento":0,"dataDocumento":"2021-11-19","numDocumento":"0018291300","valorDocumento":375.15,"urlDocumento":"https://www.camara.leg.br/cota-parlamentar/documentos/publ/2995/2021/7302356.pdf","nomeFornecedor":"CLARO NXT TELECOMUNICAÇÕES S.A. - NET","cnpjCpfFornecedor":"66970229000167","valorLiquido":375.15,"valorGlosa":0.0,"numRessarcimento":"","codLote":1815216,"parcela":0},{"ano":2021,"mes":12,"tipoDespesa":"MANUTENÇÃO DE ESCRITÓRIO DE APOIO À ATIVIDADE PARLAMENTAR","codDocumento":7314768,"tipoDocumento":"Nota Fiscal","codTipoDocumento":0,"dataDocumento":"2021-12-18","numDocumento":"0022353758","valorDocumento":373.99,"urlDocumento":"https://www.camara.leg.br/cota-parlamentar/documentos/publ/2995/2022/7314768.pdf","nomeFornecedor":"Claro S.A - Embratel","cnpjCpfFornecedor":"40432544000147","valorLiquido":373.99,"valorGlosa":0.0,"numRessarcimento":"","codLote":1820954,"parcela":0},{"ano":2021,"mes":1,"tipoDespesa":"MANUTENÇÃO DE ESCRITÓRIO DE APOIO À ATIVIDADE PARLAMENTAR","codDocumento":7155629,"tipoDocumento":"Nota Fiscal","codTipoDocumento":0,"dataDocumento":"2021-01-20","numDocumento":"0000636658","valorDocumento":384.28,"urlDocumento":"https://www.camara.leg.br/cota-parlamentar/documentos/publ/2995/2021/7155629.pdf","nomeFornecedor":"Claro S.A - NET","cnpjCpfFornecedor":"40432544000147","valorLiquido":368.72,"valorGlosa":15.56,"numRessarcimento":"","codLote":1746041,"parcela":0},{"ano":2021,"mes":2,"tipoDespesa":"MANUTENÇÃO DE ESCRITÓRIO DE APOIO À ATIVIDADE PARLAMENTAR","codDocumento":7169450,"tipoDocumento":"Nota Fiscal","codTipoDocumento":0,"dataDocumento":"2021-02-19","numDocumento":"0001503963","valorDocumento":404.93,"urlDocumento":"https://www.camara.leg.br/cota-parlamentar/documentos/publ/2995/2021/7169450.pdf","nomeFornecedor":"Claro S.A - NET","cnpjCpfFornecedor":"40432544000147","valorLiquido":396.74,"valorGlosa":8.19,"numRessarcimento":"","codLote":1753595,"parcela":0},{"ano":2021,"mes":3,"tipoDespesa":"MANUTENÇÃO DE ESCRITÓRIO DE APOIO À ATIVIDADE PARLAMENTAR","codDocumento":7179010,"tipoDocumento":"Nota Fiscal","codTipoDocumento":0,"dataDocumento":"2021-03-18","numDocumento":"0006248378","valorDocumento":392.45,"urlDocumento":"https://www.camara.leg.br/cota-parlamentar/documentos/publ/2995/2021/7179010.pdf","nomeFornecedor":"Claro S.A - NET","cnpjCpfFornecedor":"40432544000147","valorLiquido":392.45,"valorGlosa":0.0,"numRessarcimento":"","codLote":1758224,"parcela":0},{"ano":2021,"mes":4,"tipoDespesa":"MANUTENÇÃO DE ESCRITÓRIO DE APOIO À ATIVIDADE PARLAMENTAR","codDocumento":7194878,"tipoDocumento":"Nota Fiscal","codTipoDocumento":0,"dataDocumento":"2021-04-16","numDocumento":"0010613766","valorDocumento":381.18,"urlDocumento":"https://www.camara.leg.br/cota-parlamentar/documentos/publ/2995/2021/7194878.pdf","nomeFornecedor":"Claro S.A - NET","cnpjCpfFornecedor":"40432544000147","valorLiquido":364.75,"valorGlosa":16.43,"numRessarcimento":"","codLote":1765579,"parcela":0},{"ano":2021,"mes":5,"tipoDespesa":"MANUTENÇÃO DE ESCRITÓRIO DE APOIO À ATIVIDADE PARLAMENTAR","codDocumento":7204731,"tipoDocumento":"Nota Fiscal","codTipoDocumento":0,"dataDocumento":"2021-05-21","numDocumento":"0015354210","valorDocumento":370.31,"urlDocumento":"https://www.camara.leg.br/cota-parlamentar/documentos/publ/2995/2021/7204731.pdf","nomeFornecedor":"Claro S.A - NET","cnpjCpfFornecedor":"40432544000147","valorLiquido":362.55,"valorGlosa":7.76,"numRessarcimento":"","codLote":1770221,"parcela":0},{"ano":2021,"mes":6,"tipoDespesa":"MANUTENÇÃO DE ESCRITÓRIO DE APOIO À ATIVIDADE PARLAMENTAR","codDocumento":7227242,"tipoDocumento":"Nota Fiscal","codTipoDocumento":0,"dataDocumento":"2021-06-18","numDocumento":"0019767825","valorDocumento":368.86,"urlDocumento":"https://www.camara.leg.br/cota-parlamentar/documentos/publ/2995/2021/7227242.pdf","nomeFornecedor":"Claro S.A - NET","cnpjCpfFornecedor":"40432544000147","valorLiquido":362.3,"valorGlosa":6.56,"numRessarcimento":"","codLote":1781321,"parcela":0},{"ano":2021,"mes":5,"tipoDespesa":"MANUTENÇÃO DE ESCRITÓRIO DE APOIO À ATIVIDADE PARLAMENTAR","codDocumento":7214748,"tipoDocumento":"Nota Fiscal","codTipoDocumento":0,"dataDocumento":"2021-05-28","numDocumento":"109796154","valorDocumento":104.81,"urlDocumento":"https://www.camara.leg.br/cota-parlamentar/documentos/publ/2995/2021/7214748.pdf","nomeFornecedor":"ELEKTRO REDES S.A.","cnpjCpfFornecedor":"02328280000197","valorLiquido":97.52,"valorGlosa":7.29,"numRessarcimento":"","codLote":1775839,"parcela":0},{"ano":2021,"mes":10,"tipoDespesa":"MANUTENÇÃO DE ESCRITÓRIO DE APOIO À ATIVIDADE PARLAMENTAR","codDocumento":7291679,"tipoDocumento":"Nota Fiscal","codTipoDocumento":0,"dataDocumento":"2021-10-28","numDocumento":"123571399","valorDocumento":277.43,"urlDocumento":"https://www.camara.leg.br/cota-parlamentar/documentos/publ/2995/2021/7291679.pdf","nomeFornecedor":"ELEKTRO REDES S.A.","cnpjCpfFornecedor":"02328280000197","valorLiquido":272.14,"valorGlosa":5.29,"numRessarcimento":"","codLote":1810456,"parcela":0},{"ano":2021,"mes":11,"tipoDespesa":"MANUTENÇÃO DE ESCRITÓRIO DE APOIO À ATIVIDADE PARLAMENTAR","codDocumento":7310910,"tipoDocumento":"Nota Fiscal","codTipoDocumento":0,"dataDocumento":"2021-11-29","numDocumento":"126449172","valorDocumento":370.52,"urlDocumento":"https://www.camara.leg.br/cota-parlamentar/documentos/publ/2995/2021/7310910.pdf","nomeFornecedor":"ELEKTRO REDES S.A.","cnpjCpfFornecedor":"02328280000197","valorLiquido":370.52,"valorGlosa":0.0,"numRessarcimento":"","codLote":1819059,"parcela":0},{"ano":2021,"mes":6,"tipoDespesa":"MANUTENÇÃO DE ESCRITÓRIO DE APOIO À ATIVIDADE PARLAMENTAR","codDocumento":7225468,"tipoDocumento":"Nota Fiscal","codTipoDocumento":0,"dataDocumento":"2021-06-29","numDocumento":"16620097","valorDocumento":320.83,"urlDocumento":"https://www.camara.leg.br/cota-parlamentar/documentos/publ/2995/2021/7225468.pdf","nomeFornecedor":"ELEKTRO REDES S.A.","cnpjCpfFornecedor":"02328280000197","valorLiquido":316.88,"valorGlosa":3.95,"numRessarcimento":"","codLote":1780540,"parcela":0},{"ano":2021,"mes":5,"tipoDespesa":"MANUTENÇÃO DE ESCRITÓRIO DE APOIO À ATIVIDADE PARLAMENTAR","codDocumento":7214733,"tipoDocumento":"Nota Fiscal","codTipoDocumento":0,"dataDocumento":"2021-05-28","numDocumento":"37782371","valorDocumento":99.26,"urlDocumento":"https://www.camara.leg.br/cota-parlamentar/documentos/publ/2995/2021/7214733.pdf","nomeFornecedor":"ELEKTRO REDES S.A.","cnpjCpfFornecedor":"02328280000197","valorLiquido":95.05,"valorGlosa":4.21,"numRessarcimento":"","codLote":1775310,"parcela":0},{"ano":2021,"mes":11,"tipoDespesa":"MANUTENÇÃO DE ESCRITÓRIO DE APOIO À ATIVIDADE PARLAMENTAR","codDocumento":7310915,"tipoDocumento":"Nota Fiscal","codTipoDocumento":0,"dataDocumento":"2021-11-29","numDocumento":"37782371","valorDocumento":336.05,"urlDocumento":"https://www.camara.leg.br/cota-parlamentar/documentos/publ/2995/2021/7310915.pdf","nomeFornecedor":"ELEKTRO REDES S.A.","cnpjCpfFornecedor":"02328280000197","valorLiquido":336.05,"valorGlosa":0.0,"numRessarcimento":"","codLote":1819284,"parcela":0},{"ano":2021,"mes":1,"tipoDespesa":"MANUTENÇÃO DE ESCRITÓRIO DE APOIO À ATIVIDADE PARLAMENTAR","codDocumento":7159318,"tipoDocumento":"Nota Fiscal","codTipoDocumento":0,"dataDocumento":"2021-01-28","numDocumento":"098782603","valorDocumento":741.5,"urlDocumento":"https://www.camara.leg.br/cota-parlamentar/documentos/publ/2995/2021/7159318.pdf","nomeFornecedor":"ELEKTRO REDES S.A.","cnpjCpfFornecedor":"02328280000278","valorLiquido":696.32,"valorGlosa":45.18,"numRessarcimento":"","codLote":1747785,"parcela":0},{"ano":2021,"mes":2,"tipoDespesa":"MANUTENÇÃO DE ESCRITÓRIO DE APOIO À ATIVIDADE PARLAMENTAR","codDocumento":7169441,"tipoDocumento":"Nota Fiscal","codTipoDocumento":0,"dataDocumento":"2021-02-24","numDocumento":"101355414","valorDocumento":265.56,"urlDocumento":"https://www.camara.leg.br/cota-parlamentar/documentos/publ/2995/2021/7169441.pdf","nomeFornecedor":"ELEKTRO REDES S.A.","cnpjCpfFornecedor":"02328280000278","valorLiquido":265.56,"valorGlosa":0.0,"numRessarcimento":"","codLote":1753595,"parcela":0},{"ano":2021,"mes":2,"tipoDespesa":"MANUTENÇÃO DE ESCRITÓRIO DE APOIO À ATIVIDADE PARLAMENTAR","codDocumento":7169438,"tipoDocumento":"Nota Fiscal","codTipoDocumento":0,"dataDocumento":"2021-02-25","numDocumento":"101463419","valorDocumento":360.26,"urlDocumento":"https://www.camara.leg.br/cota-parlamentar/documentos/publ/2995/2021/7169438.pdf","nomeFornecedor":"ELEKTRO REDES S.A.","cnpjCpfFornecedor":"02328280000278","valorLiquido":360.26,"valorGlosa":0.0,"numRessarcimento":"","codLote":1753332,"parcela":0},{"ano":2021,"mes":3,"tipoDespesa":"MANUTENÇÃO DE ESCRITÓRIO DE APOIO À ATIVIDADE PARLAMENTAR","codDocumento":7181894,"tipoDocumento":"Nota Fiscal","codTipoDocumento":0,"dataDocumento":"2021-03-29","numDocumento":"104313818","valorDocumento":331.54,"urlDocumento":"https://www.camara.leg.br/cota-parlamentar/documentos/publ/2995/2021/7181894.pdf","nomeFornecedor":"ELEKTRO REDES S.A.","cnpjCpfFornecedor":"02328280000278","valorLiquido":313.74,"valorGlosa":17.8,"numRessarcimento":"","codLote":1759597,"parcela":0},{"ano":2021,"mes":3,"tipoDespesa":"MANUTENÇÃO DE ESCRITÓRIO DE APOIO À ATIVIDADE PARLAMENTAR","codDocumento":7181891,"tipoDocumento":"Nota Fiscal","codTipoDocumento":0,"dataDocumento":"2021-03-29","numDocumento":"104313839","valorDocumento":395.27,"urlDocumento":"https://www.camara.leg.br/cota-parlamentar/documentos/publ/2995/2021/7181891.pdf","nomeFornecedor":"ELEKTRO REDES S.A.","cnpjCpfFornecedor":"02328280000278","valorLiquido":358.98,"valorGlosa":36.29,"numRessarcimento":"","codLote":1759591,"parcela":0},{"ano":2021,"mes":4,"tipoDespesa":"MANUTENÇÃO DE ESCRITÓRIO DE APOIO À ATIVIDADE PARLAMENTAR","codDocumento":7202531,"tipoDocumento":"Nota Fiscal","codTipoDocumento":0,"dataDocumento":"2021-04-29","numDocumento":"106976753","valorDocumento":263.86,"urlDocumento":"https://www.camara.leg.br/cota-parlamentar/documentos/publ/2995/2021/7202531.pdf","nomeFornecedor":"ELEKTRO REDES S.A.","cnpjCpfFornecedor":"02328280000278","valorLiquido":254.31,"valorGlosa":9.55,"numRessarcimento":"","codLote":1769158,"parcela":0},{"ano":2021,"mes":4,"tipoDespesa":"MANUTENÇÃO DE ESCRITÓRIO DE APOIO À ATIVIDADE PARLAMENTAR","codDocumento":7199497,"tipoDocumento":"Nota Fiscal","codTipoDocumento":0,"dataDocumento":"2021-04-29","numDocumento":"107041524","valorDocumento":302.53,"urlDocumento":"https://www.camara.leg.br/cota-parlamentar/documentos/publ/2995/2021/7199497.pdf","nomeFornecedor":"ELEKTRO REDES S.A.","cnpjCpfFornecedor":"02328280000278","valorLiquido":291.68,"valorGlosa":10.85,"numRessarcimento":"","codLote":1767686,"parcela":0},{"ano":2021,"mes":7,"tipoDespesa":"MANUTENÇÃO DE ESCRITÓRIO DE APOIO À ATIVIDADE PARLAMENTAR","codDocumento":7245693,"tipoDocumento":"Nota Fiscal","codTipoDocumento":0,"dataDocumento":"2021-07-29","numDocumento":"115261518","valorDocumento":94.91,"urlDocumento":"https://www.camara.leg.br/cota-parlamentar/documentos/publ/2995/2021/7245693.pdf","nomeFornecedor":"ELEKTRO REDES S.A.","cnpjCpfFornecedor":"02328280000278","valorLiquido":94.91,"valorGlosa":0.0,"numRessarcimento":"","codLote":1789533,"parcela":0},{"ano":2021,"mes":8,"tipoDespesa":"MANUTENÇÃO DE ESCRITÓRIO DE APOIO À ATIVIDADE PARLAMENTAR","codDocumento":7258266,"tipoDocumento":"Nota Fiscal","codTipoDocumento":0,"dataDocumento":"2021-08-26","numDocumento":"118026828","valorDocumento":75.38,"urlDocumento":"https://www.camara.leg.br/cota-parlamentar/documentos/publ/2995/2021/7258266.pdf","nomeFornecedor":"ELEKTRO REDES S.A.","cnpjCpfFornecedor":"02328280000278","valorLiquido":73.44,"valorGlosa":1.94,"numRessarcimento":"","codLote":1795362,"parcela":0},{"ano":2021,"mes":9,"tipoDespesa":"MANUTENÇÃO DE ESCRITÓRIO DE APOIO À ATIVIDADE PARLAMENTAR","codDocumento":7272113,"tipoDocumento":"Nota Fiscal","codTipoDocumento":0,"dataDocumento":"2021-09-28","numDocumento":"120821445","valorDocumento":242.93,"urlDocumento":"https://www.camara.leg.br/cota-parlamentar/documentos/publ/2995/2021/7272113.pdf","nomeFornecedor":"ELEKTRO REDES S.A.","cnpjCpfFornecedor":"02328280000278","valorLiquido":241.26,"valorGlosa":1.67,"numRessarcimento":"","codLote":1801753,"parcela":0},{"ano":2021,"mes":9,"tipoDespesa":"MANUTENÇÃO DE ESCRITÓRIO DE APOIO À ATIVIDADE PARLAMENTAR","codDocumento":7272076,"tipoDocumento":"Nota Fiscal","codTipoDocumento":0,"dataDocumento":"2021-09-28","numDocumento":"120821502","valorDocumento":258.67,"urlDocumento":"https://www.camara.leg.br/cota-parlamentar/documentos/publ/2995/2021/7272076.pdf","nomeFornecedor":"ELEKTRO REDES S.A.","cnpjCpfFornecedor":"02328280000278","valorLiquido":257.1,"valorGlosa":1.57,"numRessarcimento":"","codLote":1801528,"parcela":0},{"ano":2021,"mes":10,"tipoDespesa":"MANUTENÇÃO DE ESCRITÓRIO DE APOIO À ATIVIDADE PARLAMENTAR","codDocumento":7289575,"tipoDocumento":"Nota Fiscal","codTipoDocumento":0,"dataDocumento":"2021-10-28","numDocumento":"123571421","valorDocumento":281.98,"urlDocumento":"https://www.camara.leg.br/cota-parlamentar/documentos/publ/2995/2021/7289575.pdf","nomeFornecedor":"ELEKTRO REDES S.A.","cnpjCpfFornecedor":"02328280000278","valorLiquido":276.35,"valorGlosa":5.63,"numRessarcimento":"","codLote":1809238,"parcela":0},{"ano":2021,"mes":12,"tipoDespesa":"MANUTENÇÃO DE ESCRITÓRIO DE APOIO À ATIVIDADE PARLAMENTAR","codDocumento":7315807,"tipoDocumento":"Nota Fiscal","codTipoDocumento":0,"dataDocumento":"2021-12-29","numDocumento":"129203936","valorDocumento":387.45,"urlDocumento":"https://www.camara.leg.br/cota-parlamentar/documentos/publ/2995/2022/7315807.pdf","nomeFornecedor":"ELEKTRO REDES S.A.","cnpjCpfFornecedor":"02328280000278","valorLiquido":379.19,"valorGlosa":8.26,"numRessarcimento":"","codLote":1821558,"parcela":0},{"ano":2021,"mes":8,"tipoDespesa":"MANUTENÇÃO DE ESCRITÓRIO DE APOIO À ATIVIDADE PARLAMENTAR","codDocumento":7258248,"tipoDocumento":"Nota Fiscal","codTipoDocumento":0,"dataDocumento":"2021-08-26","numDocumento":"16620097","valorDocumento":74.3,"urlDocumento":"https://www.camara.leg.br/cota-parlamentar/documentos/publ/2995/2021/7258248.pdf","nomeFornecedor":"ELEKTRO REDES S.A.","cnpjCpfFornecedor":"02328280000278","valorLiquido":74.3,"valorGlosa":0.0,"numRessarcimento":"","codLote":1795357,"parcela":0},{"ano":2021,"mes":12,"tipoDespesa":"MANUTENÇÃO DE ESCRITÓRIO DE APOIO À ATIVIDADE PARLAMENTAR","codDocumento":7315806,"tipoDocumento":"Nota Fiscal","codTipoDocumento":0,"dataDocumento":"2021-12-29","numDocumento":"37782371","valorDocumento":413.0,"urlDocumento":"https://www.camara.leg.br/cota-parlamentar/documentos/publ/2995/2022/7315806.pdf","nomeFornecedor":"ELEKTRO REDES S.A.","cnpjCpfFornecedor":"02328280000278","valorLiquido":412.24,"valorGlosa":0.76,"numRessarcimento":"","codLote":1821406,"parcela":0},{"ano":2021,"mes":1,"tipoDespesa":"MANUTENÇÃO DE ESCRITÓRIO DE APOIO À ATIVIDADE PARLAMENTAR","codDocumento":7159315,"tipoDocumento":"Nota Fiscal","codTipoDocumento":0,"dataDocumento":"2021-01-27","numDocumento":"98617467","valorDocumento":289.09,"urlDocumento":"https://www.camara.leg.br/cota-parlamentar/documentos/publ/2995/2021/7159315.pdf","nomeFornecedor":"ELEKTRO REDES S.A.","cnpjCpfFornecedor":"02328280000278","valorLiquido":279.63,"valorGlosa":9.46,"numRessarcimento":"","codLote":1747798,"parcela":0},{"ano":2021,"mes":4,"tipoDespesa":"MANUTENÇÃO DE ESCRITÓRIO DE APOIO À ATIVIDADE PARLAMENTAR","codDocumento":7199505,"tipoDocumento":"Nota Fiscal","codTipoDocumento":0,"dataDocumento":"2021-04-29","numDocumento":"40325","valorDocumento":105.0,"urlDocumento":"https://www.camara.leg.br/cota-parlamentar/documentos/publ/2995/2021/7199505.pdf","nomeFornecedor":"GRAFFIT LIMEIRA PAPELARIA LTDA","cnpjCpfFornecedor":"68917061000151","valorLiquido":105.0,"valorGlosa":0.0,"numRessarcimento":"","codLote":1767686,"parcela":0},{"ano":2021,"mes":3,"tipoDespesa":"MANUTENÇÃO DE ESCRITÓRIO DE APOIO À ATIVIDADE PARLAMENTAR","codDocumento":7178362,"tipoDocumento":"Nota Fiscal","codTipoDocumento":0,"dataDocumento":"2021-03-04","numDocumento":"39817","valorDocumento":291.08,"urlDocumento":"https://www.camara.leg.br/cota-parlamentar/documentos/publ/2995/2021/7178362.pdf","nomeFornecedor":"Graffit Limeira Papelaria Ltda Me","cnpjCpfFornecedor":"68917061000151","valorLiquido":291.08,"valorGlosa":0.0,"numRessarcimento":"","codLote":1757923,"parcela":0},{"ano":2021,"mes":6,"tipoDespesa":"MANUTENÇÃO DE ESCRITÓRIO DE APOIO À ATIVIDADE PARLAMENTAR","codDocumento":7226056,"tipoDocumento":"Nota Fiscal","codTipoDocumento":0,"dataDocumento":"2021-06-28","numDocumento":"40957","valorDocumento":210.0,"urlDocumento":"https://www.camara.leg.br/cota-parlamentar/documentos/publ/2995/2021/7226056.pdf","nomeFornecedor":"Graffit Limeira Papelaria Ltda Me","cnpjCpfFornecedor":"68917061000151","valorLiquido":210.0,"valorGlosa":0.0,"numRessarcimento":"","codLote":1780830,"parcela":0},{"ano":2021,"mes":7,"tipoDespesa":"MANUTENÇÃO DE ESCRITÓRIO DE APOIO À ATIVIDADE PARLAMENTAR","codDocumento":7242774,"tipoDocumento":"Nota Fiscal","codTipoDocumento":0,"dataDocumento":"2021-07-15","numDocumento":"41131","valorDocumento":122.4,"urlDocumento":"https://www.camara.leg.br/cota-parlamentar/documentos/publ/2995/2021/7242774.pdf","nomeFornecedor":"Graffit Limeira Papelaria Ltda Me","cnpjCpfFornecedor":"68917061000151","valorLiquido":122.4,"valorGlosa":0.0,"numRessarcimento":"","codLote":1788265,"parcela":0},{"ano":2021,"mes":7,"tipoDespesa":"MANUTENÇÃO DE ESCRITÓRIO DE APOIO À ATIVIDADE PARLAMENTAR","codDocumento":7242770,"tipoDocumento":"Nota Fiscal","codTipoDocumento":0,"dataDocumento":"2021-07-22","numDocumento":"41203","valorDocumento":124.4,"urlDocumento":"https://www.camara.leg.br/cota-parlamentar/documentos/publ/2995/2021/7242770.pdf","nomeFornecedor":"Graffit Limeira Papelaria Ltda Me","cnpjCpfFornecedor":"68917061000151","valorLiquido":124.4,"valorGlosa":0.0,"numRessarcimento":"","codLote":1788265,"parcela":0},{"ano":2021,"mes":8,"tipoDespesa":"MANUTENÇÃO DE ESCRITÓRIO DE APOIO À ATIVIDADE PARLAMENTAR","codDocumento":7257660,"tipoDocumento":"Nota Fiscal","codTipoDocumento":0,"dataDocumento":"2021-08-19","numDocumento":"41494","valorDocumento":1183.71,"urlDocumento":"https://www.camara.leg.br/cota-parlamentar/documentos/publ/2995/2021/7257660.pdf","nomeFornecedor":"Graffit Limeira Papelaria Ltda Me","cnpjCpfFornecedor":"68917061000151","valorLiquido":1183.71,"valorGlosa":0.0,"numRessarcimento":"","codLote":1795166,"parcela":0},{"ano":2021,"mes":10,"tipoDespesa":"MANUTENÇÃO DE ESCRITÓRIO DE APOIO À ATIVIDADE PARLAMENTAR","codDocumento":7289588,"tipoDocumento":"Nota Fiscal","codTipoDocumento":0,"dataDocumento":"2021-10-14","numDocumento":"42093","valorDocumento":195.0,"urlDocumento":"https://www.camara.leg.br/cota-parlamentar/documentos/publ/2995/2021/7289588.pdf","nomeFornecedor":"Graffit Limeira Papelaria Ltda Me","cnpjCpfFornecedor":"68917061000151","valorLiquido":195.0,"valorGlosa":0.0,"numRessarcimento":"","codLote":1809238,"parcela":0},{"ano":2021,"mes":11,"tipoDespesa":"MANUTENÇÃO DE ESCRITÓRIO DE APOIO À ATIVIDADE PARLAMENTAR","codDocumento":7310538,"tipoDocumento":"Nota Fiscal","codTipoDocumento":0,"dataDocumento":"2021-11-16","numDocumento":"42437","valorDocumento":1425.8,"urlDocumento":"https://www.camara.leg.br/cota-parlamentar/documentos/publ/2995/2021/7310538.pdf","nomeFornecedor":"Graffit Limeira Papelaria Ltda Me","cnpjCpfFornecedor":"68917061000151","valorLiquido":1425.8,"valorGlosa":0.0,"numRessarcimento":"","codLote":1819060,"parcela":0},{"ano":2021,"mes":11,"tipoDespesa":"MANUTENÇÃO DE ESCRITÓRIO DE APOIO À ATIVIDADE PARLAMENTAR","codDocumento":7314806,"tipoDocumento":"Nota Fiscal","codTipoDocumento":0,"dataDocumento":"2021-11-30","numDocumento":"42585","valorDocumento":280.4,"urlDocumento":"https://www.camara.leg.br/cota-parlamentar/documentos/publ/2995/2022/7314806.pdf","nomeFornecedor":"Graffit Limeira Papelaria Ltda Me","cnpjCpfFornecedor":"68917061000151","valorLiquido":280.4,"valorGlosa":0.0,"numRessarcimento":"","codLote":1820953,"parcela":0},{"ano":2021,"mes":12,"tipoDespesa":"MANUTENÇÃO DE ESCRITÓRIO DE APOIO À ATIVIDADE PARLAMENTAR","codDocumento":7315049,"tipoDocumento":"Nota Fiscal","codTipoDocumento":0,"dataDocumento":"2021-12-16","numDocumento":"42791","valorDocumento":140.2,"urlDocumento":"https://www.camara.leg.br/cota-parlamentar/documentos/publ/2995/2022/7315049.pdf","nomeFornecedor":"Graffit Limeira Papelaria Ltda Me","cnpjCpfFornecedor":"68917061000151","valorLiquido":140.2,"valorGlosa":0.0,"numRessarcimento":"","codLote":1821064,"parcela":0},{"ano":2021,"mes":7,"tipoDespesa":"MANUTENÇÃO DE ESCRITÓRIO DE APOIO À ATIVIDADE PARLAMENTAR","codDocumento":7227246,"tipoDocumento":"Nota Fiscal","codTipoDocumento":0,"dataDocumento":"2021-07-20","numDocumento":"017158","valorDocumento":145.0,"urlDocumento":"https://www.camara.leg.br/cota-parlamentar/documentos/publ/2995/2021/7227246.pdf","nomeFornecedor":"PAPELARIA BELA VISTA LTDA ME","cnpjCpfFornecedor":"05594776000109","valorLiquido":145.0,"valorGlosa":0.0,"numRessarcimento":"","codLote":1781802,"parcela":0},{"ano":2021,"mes":3,"tipoDespesa":"MANUTENÇÃO DE ESCRITÓRIO DE APOIO À ATIVIDADE PARLAMENTAR","codDocumento":7164533,"tipoDocumento":"Nota Fiscal","codTipoDocumento":0,"dataDocumento":"2021-03-04","numDocumento":"1677","valorDocumento":161.0,"urlDocumento":"https://www.camara.leg.br/cota-parlamentar/documentos/publ/2995/2021/7164533.pdf","nomeFornecedor":"PAPELARIA BELA VISTA LTDA ME","cnpjCpfFornecedor":"05594776000109","valorLiquido":161.0,"valorGlosa":0.0,"numRessarcimento":"","codLote":1750915,"parcela":0},{"ano":2021,"mes":11,"tipoDespesa":"MANUTENÇÃO DE ESCRITÓRIO DE APOIO À ATIVIDADE PARLAMENTAR","codDocumento":7291250,"tipoDocumento":"Nota Fiscal","codTipoDocumento":0,"dataDocumento":"2021-11-18","numDocumento":"1820","valorDocumento":175.0,"urlDocumento":"https://www.camara.leg.br/cota-parlamentar/documentos/publ/2995/2021/7291250.pdf","nomeFornecedor":"PAPELARIA BELA VISTA LTDA ME","cnpjCpfFornecedor":"05594776000109","valorLiquido":175.0,"valorGlosa":0.0,"numRessarcimento":"","codLote":1810034,"parcela":0},{"ano":2021,"mes":12,"tipoDespesa":"MANUTENÇÃO DE ESCRITÓRIO DE APOIO À ATIVIDADE PARLAMENTAR","codDocumento":7311934,"tipoDocumento":"Nota Fiscal","codTipoDocumento":0,"dataDocumento":"2021-12-28","numDocumento":"1844","valorDocumento":625.5,"urlDocumento":"https://www.camara.leg.br/cota-parlamentar/documentos/publ/2995/2021/7311934.pdf","nomeFornecedor":"PAPELARIA BELA VISTA LTDA ME","cnpjCpfFornecedor":"05594776000109","valorLiquido":625.5,"valorGlosa":0.0,"numRessarcimento":"","codLote":1819513,"parcela":0},{"ano":2021,"mes":2,"tipoDespesa":"MANUTENÇÃO DE ESCRITÓRIO DE APOIO À ATIVIDADE PARLAMENTAR","codDocumento":7169435,"tipoDocumento":"Nota Fiscal","codTipoDocumento":0,"dataDocumento":"2021-02-12","numDocumento":"74146","valorDocumento":620.9,"urlDocumento":"https://www.camara.leg.br/cota-parlamentar/documentos/publ/2995/2021/7169435.pdf","nomeFornecedor":"TECNICA INFORMATICA COMERCIO E REPRESENTACOES LTDA","cnpjCpfFornecedor":"64905359000190","valorLiquido":620.9,"valorGlosa":0.0,"numRessarcimento":"","codLote":1753595,"parcela":0},{"ano":2021,"mes":2,"tipoDespesa":"MANUTENÇÃO DE ESCRITÓRIO DE APOIO À ATIVIDADE PARLAMENTAR","codDocumento":7177424,"tipoDocumento":"Nota Fiscal","codTipoDocumento":0,"dataDocumento":"2021-02-25","numDocumento":"74400","valorDocumento":142.2,"urlDocumento":"https://www.camara.leg.br/cota-parlamentar/documentos/publ/2995/2021/7177424.pdf","nomeFornecedor":"TECNICA INFORMATICA COMERCIO E REPRESENTACOES LTDA","cnpjCpfFornecedor":"64905359000190","valorLiquido":142.2,"valorGlosa":0.0,"numRessarcimento":"","codLote":1757473,"parcela":0},{"ano":2021,"mes":4,"tipoDespesa":"MANUTENÇÃO DE ESCRITÓRIO DE APOIO À ATIVIDADE PARLAMENTAR","codDocumento":7199416,"tipoDocumento":"Nota Fiscal","codTipoDocumento":0,"dataDocumento":"2021-04-30","numDocumento":"75407","valorDocumento":235.4,"urlDocumento":"https://www.camara.leg.br/cota-parlamentar/documentos/publ/2995/2021/7199416.pdf","nomeFornecedor":"TECNICA INFORMATICA COMERCIO E REPRESENTACOES LTDA","cnpjCpfFornecedor":"64905359000190","valorLiquido":235.4,"valorGlosa":0.0,"numRessarcimento":"","codLote":1767686,"parcela":0},{"ano":2021,"mes":8,"tipoDespesa":"MANUTENÇÃO DE ESCRITÓRIO DE APOIO À ATIVIDADE PARLAMENTAR","codDocumento":7258239,"tipoDocumento":"Nota Fiscal","codTipoDocumento":0,"dataDocumento":"2021-08-18","numDocumento":"77093","valorDocumento":565.8,"urlDocumento":"https://www.camara.leg.br/cota-parlamentar/documentos/publ/2995/2021/7258239.pdf","nomeFornecedor":"TECNICA INFORMATICA COMERCIO E REPRESENTACOES LTDA","cnpjCpfFornecedor":"64905359000190","valorLiquido":565.8,"valorGlosa":0.0,"numRessarcimento":"","codLote":1795357,"parcela":0},{"ano":2021,"mes":11,"tipoDespesa":"MANUTENÇÃO DE ESCRITÓRIO DE APOIO À ATIVIDADE PARLAMENTAR","codDocumento":7309565,"tipoDocumento":"Nota Fiscal","codTipoDocumento":0,"dataDocumento":"2021-11-12","numDocumento":"78492","valorDocumento":499.9,"urlDocumento":"https://www.camara.leg.br/cota-parlamentar/documentos/publ/2995/2021/7309565.pdf","nomeFornecedor":"TECNICA INFORMATICA COMERCIO E REPRESENTACOES LTDA","cnpjCpfFornecedor":"64905359000190","valorLiquido":499.9,"valorGlosa":0.0,"numRessarcimento":"","codLote":1819059,"parcela":0},{"ano":2021,"mes":11,"tipoDespesa":"MANUTENÇÃO DE ESCRITÓRIO DE APOIO À ATIVIDADE PARLAMENTAR","codDocumento":7314816,"tipoDocumento":"Nota Fiscal","codTipoDocumento":0,"dataDocumento":"2021-11-30","numDocumento":"78823","valorDocumento":278.0,"urlDocumento":"https://www.camara.leg.br/cota-parlamentar/documentos/publ/2995/2022/7314816.pdf","nomeFornecedor":"TECNICA INFORMATICA COMERCIO E REPRESENTACOES LTDA","cnpjCpfFornecedor":"64905359000190","valorLiquido":278.0,"valorGlosa":0.0,"numRessarcimento":"","codLote":1820953,"parcela":0},{"ano":2021,"mes":12,"tipoDespesa":"MANUTENÇÃO DE ESCRITÓRIO DE APOIO À ATIVIDADE PARLAMENTAR","codDocumento":7315048,"tipoDocumento":"Nota Fiscal","codTipoDocumento":0,"dataDocumento":"2021-12-10","numDocumento":"78991","valorDocumento":279.1,"urlDocumento":"https://www.camara.leg.br/cota-parlamentar/documentos/publ/2995/2022/7315048.pdf","nomeFornecedor":"TECNICA INFORMATICA COMERCIO E REPRESENTACOES LTDA","cnpjCpfFornecedor":"64905359000190","valorLiquido":279.1,"valorGlosa":0.0,"numRessarcimento":"","codLote":1821064,"parcela":0},{"ano":2021,"mes":1,"tipoDespesa":"MANUTENÇÃO DE ESCRITÓRIO DE APOIO À ATIVIDADE PARLAMENTAR","codDocumento":7154680,"tipoDocumento":"Nota Fiscal","codTipoDocumento":0,"dataDocumento":"2021-01-08","numDocumento":"15232","valorDocumento":409.0,"urlDocumento":"https://www.camara.leg.br/cota-parlamentar/documentos/publ/2995/2021/7154680.pdf","nomeFornecedor":"Tecnica Informática LTDA","cnpjCpfFornecedor":"03935078000196","valorLiquido":409.0,"valorGlosa":0.0,"numRessarcimento":"","codLote":1747026,"parcela":0},{"ano":2021,"mes":3,"tipoDespesa":"MANUTENÇÃO DE ESCRITÓRIO DE APOIO À ATIVIDADE PARLAMENTAR","codDocumento":7178356,"tipoDocumento":"Nota Fiscal","codTipoDocumento":0,"dataDocumento":"2021-03-03","numDocumento":"15318","valorDocumento":135.0,"urlDocumento":"https://www.camara.leg.br/cota-parlamentar/documentos/publ/2995/2021/7178356.pdf","nomeFornecedor":"Tecnica Informática LTDA","cnpjCpfFornecedor":"03935078000196","valorLiquido":135.0,"valorGlosa":0.0,"numRessarcimento":"","codLote":1757923,"parcela":0},{"ano":2021,"mes":7,"tipoDespesa":"COMBUSTÍVEIS E LUBRIFICANTES.","codDocumento":7225462,"tipoDocumento":"Nota Fiscal Eletrônica","codTipoDocumento":4,"dataDocumento":"2021-07-20","numDocumento":"173005","valorDocumento":248.24,"urlDocumento":"http://www.camara.leg.br/cota-parlamentar/nota-fiscal-eletronica?ideDocumentoFiscal=7225462","nomeFornecedor":"076 - MELHOR 10 - CASCOL COMBUSTIVEIS PARA VEICULOS LTDA","cnpjCpfFornecedor":"00306597007614","valorLiquido":248.24,"valorGlosa":0.0,"numRessarcimento":"","codLote":1780538,"parcela":0},{"ano":2021,"mes":11,"tipoDespesa":"COMBUSTÍVEIS E LUBRIFICANTES.","codDocumento":7285992,"tipoDocumento":"Nota Fiscal","codTipoDocumento":0,"dataDocumento":"2021-11-04","numDocumento":"074963","valorDocumento":226.52,"urlDocumento":"https://www.camara.leg.br/cota-parlamentar/documentos/publ/2995/2021/7285992.pdf","nomeFornecedor":"AGIFLEX COMERCIO DE COMBUSTIVEIS EIRELI ME","cnpjCpfFornecedor":"23784756000174","valorLiquido":226.52,"valorGlosa":0.0,"numRessarcimento":"","codLote":1807762,"parcela":0},{"ano":2021,"mes":2,"tipoDespesa":"COMBUSTÍVEIS E LUBRIFICANTES.","codDocumento":7147400,"tipoDocumento":"Nota Fiscal Eletrônica","codTipoDocumento":4,"dataDocumento":"2021-02-01","numDocumento":"16377","valorDocumento":114.98,"urlDocumento":"http://www.camara.leg.br/cota-parlamentar/nota-fiscal-eletronica?ideDocumentoFiscal=7147400","nomeFornecedor":"AUTO POSTO 302 SUL LTDA","cnpjCpfFornecedor":"30642701000195","valorLiquido":114.98,"valorGlosa":0.0,"numRessarcimento":"","codLote":1741936,"parcela":0},{"ano":2021,"mes":2,"tipoDespesa":"COMBUSTÍVEIS E LUBRIFICANTES.","codDocumento":7151650,"tipoDocumento":"Nota Fiscal Eletrônica","codTipoDocumento":4,"dataDocumento":"2021-02-08","numDocumento":"16806","valorDocumento":184.06,"urlDocumento":"http://www.camara.leg.br/cota-parlamentar/nota-fiscal-eletronica?ideDocumentoFiscal=7151650","nomeFornecedor":"AUTO POSTO 302 SUL LTDA","cnpjCpfFornecedor":"30642701000195","valorLiquido":184.06,"valorGlosa":0.0,"numRessarcimento":"","codLote":1744068,"parcela":0},{"ano":2021,"mes":2,"tipoDespesa":"COMBUSTÍVEIS E LUBRIFICANTES.","codDocumento":7147394,"tipoDocumento":"Nota Fiscal Eletrônica","codTipoDocumento":4,"dataDocumento":"2021-02-01","numDocumento":"8984","valorDocumento":50.0,"urlDocumento":"http://www.camara.leg.br/cota-parlamentar/nota-fiscal-eletronica?ideDocumentoFiscal=7147394","nomeFornecedor":"AUTO POSTO 303 NORTE LTDA","cnpjCpfFornecedor":"38194212000120","valorLiquido":50.0,"valorGlosa":0.0,"numRessarcimento":"","codLote":1741936,"parcela":0},{"ano":2021,"mes":11,"tipoDespesa":"COMBUSTÍVEIS E LUBRIFICANTES.","codDocumento":7298357,"tipoDocumento":"Nota Fiscal Eletrônica","codTipoDocumento":4,"dataDocumento":"2021-12-02","numDocumento":"529","valorDocumento":400.0,"urlDocumento":"http://www.camara.leg.br/cota-parlamentar/nota-fiscal-eletronica?ideDocumentoFiscal=7298357","nomeFornecedor":"AUTO POSTO 305 SUL LTDA","cnpjCpfFornecedor":"32085527000152","valorLiquido":400.0,"valorGlosa":0.0,"numRessarcimento":"","codLote":1813215,"parcela":0},{"ano":2021,"mes":12,"tipoDespesa":"COMBUSTÍVEIS E LUBRIFICANTES.","codDocumento":7310542,"tipoDocumento":"Nota Fiscal Eletrônica","codTipoDocumento":4,"dataDocumento":"2021-12-23","numDocumento":"545","valorDocumento":793.48,"urlDocumento":"http://www.camara.leg.br/cota-parlamentar/nota-fiscal-eletronica?ideDocumentoFiscal=7310542","nomeFornecedor":"AUTO POSTO 305 SUL LTDA","cnpjCpfFornecedor":"32085527000152","valorLiquido":793.48,"valorGlosa":0.0,"numRessarcimento":"","codLote":1818847,"parcela":0},{"ano":2021,"mes":2,"tipoDespesa":"COMBUSTÍVEIS E LUBRIFICANTES.","codDocumento":7149899,"tipoDocumento":"Nota Fiscal Eletrônica","codTipoDocumento":4,"dataDocumento":"2021-02-03","numDocumento":"139436","valorDocumento":150.0,"urlDocumento":"http://www.camara.leg.br/cota-parlamentar/nota-fiscal-eletronica?ideDocumentoFiscal=7149899","nomeFornecedor":"AUTO POSTO 306 NORTE LTDA","cnpjCpfFornecedor":"22398818000147","valorLiquido":150.0,"valorGlosa":0.0,"numRessarcimento":"","codLote":1743168,"parcela":0},{"ano":2021,"mes":6,"tipoDespesa":"COMBUSTÍVEIS E LUBRIFICANTES.","codDocumento":7213345,"tipoDocumento":"Nota Fiscal Eletrônica","codTipoDocumento":4,"dataDocumento":"2021-06-24","numDocumento":"278294","valorDocumento":200.0,"urlDocumento":"http://www.camara.leg.br/cota-parlamentar/nota-fiscal-eletronica?ideDocumentoFiscal=7213345","nomeFornecedor":"AUTO POSTO AEROPORTO LTDA","cnpjCpfFornecedor":"08202116000115","valorLiquido":200.0,"valorGlosa":0.0,"numRessarcimento":"","codLote":1774709,"parcela":0},{"ano":2021,"mes":6,"tipoDespesa":"COMBUSTÍVEIS E LUBRIFICANTES.","codDocumento":7214910,"tipoDocumento":"Nota Fiscal","codTipoDocumento":0,"dataDocumento":"2021-06-26","numDocumento":"439434","valorDocumento":181.64,"urlDocumento":"https://www.camara.leg.br/cota-parlamentar/documentos/publ/2995/2021/7214910.pdf","nomeFornecedor":"AUTO POSTO AFA LTDA","cnpjCpfFornecedor":"38989141000151","valorLiquido":181.64,"valorGlosa":0.0,"numRessarcimento":"","codLote":1775841,"parcela":0},{"ano":2021,"mes":8,"tipoDespesa":"COMBUSTÍVEIS E LUBRIFICANTES.","codDocumento":7231232,"tipoDocumento":"Nota Fiscal","codTipoDocumento":0,"dataDocumento":"2021-08-01","numDocumento":"447728","valorDocumento":150.0,"urlDocumento":"https://www.camara.leg.br/cota-parlamentar/documentos/publ/2995/2021/7231232.pdf","nomeFornecedor":"AUTO POSTO AFA LTDA","cnpjCpfFornecedor":"38989141000151","valorLiquido":150.0,"valorGlosa":0.0,"numRessarcimento":"","codLote":1783553,"parcela":0},{"ano":2021,"mes":10,"tipoDespesa":"COMBUSTÍVEIS E LUBRIFICANTES.","codDocumento":7299334,"tipoDocumento":"Nota Fiscal","codTipoDocumento":0,"dataDocumento":"2021-10-25","numDocumento":"468909","valorDocumento":120.0,"urlDocumento":"https://www.camara.leg.br/cota-parlamentar/documentos/publ/2995/2021/7299334.pdf","nomeFornecedor":"AUTO POSTO AFA LTDA","cnpjCpfFornecedor":"38989141000151","valorLiquido":120.0,"valorGlosa":0.0,"numRessarcimento":"","codLote":1814214,"parcela":0},{"ano":2021,"mes":1,"tipoDespesa":"COMBUSTÍVEIS E LUBRIFICANTES.","codDocumento":7147397,"tipoDocumento":"Nota Fiscal Eletrônica","codTipoDocumento":4,"dataDocumento":"2021-01-31","numDocumento":"184111","valorDocumento":50.0,"urlDocumento":"http://www.camara.leg.br/cota-parlamentar/nota-fiscal-eletronica?ideDocumentoFiscal=7147397","nomeFornecedor":"AUTO POSTO AVENIDA LTDA","cnpjCpfFornecedor":"03425227000177","valorLiquido":50.0,"valorGlosa":0.0,"numRessarcimento":"","codLote":1741944,"parcela":0},{"ano":2021,"mes":2,"tipoDespesa":"COMBUSTÍVEIS E LUBRIFICANTES.","codDocumento":7159355,"tipoDocumento":"Nota Fiscal","codTipoDocumento":0,"dataDocumento":"2021-02-20","numDocumento":"012650","valorDocumento":161.01,"urlDocumento":"https://www.camara.leg.br/cota-parlamentar/documentos/publ/2995/2021/7159355.pdf","nomeFornecedor":"AUTO POSTO BANDEIRANTES LIMEIRA LTDA","cnpjCpfFornecedor":"44760601000178","valorLiquido":161.01,"valorGlosa":0.0,"numRessarcimento":"","codLote":1747795,"parcela":0},{"ano":2021,"mes":2,"tipoDespesa":"COMBUSTÍVEIS E LUBRIFICANTES.","codDocumento":7161507,"tipoDocumento":"Nota Fiscal","codTipoDocumento":0,"dataDocumento":"2021-02-27","numDocumento":"013601","valorDocumento":163.81,"urlDocumento":"https://www.camara.leg.br/cota-parlamentar/documentos/publ/2995/2021/7161507.pdf","nomeFornecedor":"AUTO POSTO BANDEIRANTES LIMEIRA LTDA","cnpjCpfFornecedor":"44760601000178","valorLiquido":163.81,"valorGlosa":0.0,"numRessarcimento":"","codLote":1748846,"parcela":0},{"ano":2021,"mes":3,"tipoDespesa":"COMBUSTÍVEIS E LUBRIFICANTES.","codDocumento":7176978,"tipoDocumento":"Nota Fiscal","codTipoDocumento":0,"dataDocumento":"2021-03-27","numDocumento":"017098","valorDocumento":231.3,"urlDocumento":"https://www.camara.leg.br/cota-parlamentar/documentos/publ/2995/2021/7176978.pdf","nomeFornecedor":"AUTO POSTO BANDEIRANTES LIMEIRA LTDA","cnpjCpfFornecedor":"44760601000178","valorLiquido":231.3,"valorGlosa":0.0,"numRessarcimento":"","codLote":1757350,"parcela":0},{"ano":2021,"mes":1,"tipoDespesa":"COMBUSTÍVEIS E LUBRIFICANTES.","codDocumento":7151749,"tipoDocumento":"Nota Fiscal","codTipoDocumento":0,"dataDocumento":"2021-01-30","numDocumento":"014701","valorDocumento":108.46,"urlDocumento":"https://www.camara.leg.br/cota-parlamentar/documentos/publ/2995/2021/7151749.pdf","nomeFornecedor":"AUTO POSTO BENEDITA DE FREITAS TADEU e CIA LTDA","cnpjCpfFornecedor":"17652049000121","valorLiquido":108.46,"valorGlosa":0.0,"numRessarcimento":"","codLote":1744119,"parcela":0},{"ano":2021,"mes":5,"tipoDespesa":"COMBUSTÍVEIS E LUBRIFICANTES.","codDocumento":7192000,"tipoDocumento":"Nota Fiscal","codTipoDocumento":0,"dataDocumento":"2021-05-03","numDocumento":"033487","valorDocumento":153.55,"urlDocumento":"https://www.camara.leg.br/cota-parlamentar/documentos/publ/2995/2021/7192000.pdf","nomeFornecedor":"AUTO POSTO BENEDITA DE FREITAS TADEU e CIA LTDA","cnpjCpfFornecedor":"17652049000121","valorLiquido":153.55,"valorGlosa":0.0,"numRessarcimento":"","codLote":1764295,"parcela":0},{"ano":2021,"mes":5,"tipoDespesa":"COMBUSTÍVEIS E LUBRIFICANTES.","codDocumento":7191316,"tipoDocumento":"Nota Fiscal","codTipoDocumento":0,"dataDocumento":"2021-05-07","numDocumento":"034515","valorDocumento":100.0,"urlDocumento":"https://www.camara.leg.br/cota-parlamentar/documentos/publ/2995/2021/7191316.pdf","nomeFornecedor":"AUTO POSTO BENEDITA DE FREITAS TADEU e CIA LTDA","cnpjCpfFornecedor":"17652049000121","valorLiquido":100.0,"valorGlosa":0.0,"numRessarcimento":"","codLote":1763989,"parcela":0},{"ano":2021,"mes":10,"tipoDespesa":"COMBUSTÍVEIS E LUBRIFICANTES.","codDocumento":7272271,"tipoDocumento":"Nota Fiscal","codTipoDocumento":0,"dataDocumento":"2021-10-04","numDocumento":"074177","valorDocumento":100.0,"urlDocumento":"https://www.camara.leg.br/cota-parlamentar/documentos/publ/2995/2021/7272271.pdf","nomeFornecedor":"AUTO POSTO BENEDITA DE FREITAS TADEU e CIA LTDA","cnpjCpfFornecedor":"17652049000121","valorLiquido":100.0,"valorGlosa":0.0,"numRessarcimento":"","codLote":1801751,"parcela":0},{"ano":2021,"mes":5,"tipoDespesa":"COMBUSTÍVEIS E LUBRIFICANTES.","codDocumento":7198184,"tipoDocumento":"Nota Fiscal","codTipoDocumento":0,"dataDocumento":"2021-05-24","numDocumento":"38725","valorDocumento":150.0,"urlDocumento":"https://www.camara.leg.br/cota-parlamentar/documentos/publ/2995/2021/7198184.pdf","nomeFornecedor":"AUTO POSTO BENEDITA DE FREITAS TADEU e CIA LTDA","cnpjCpfFornecedor":"17652049000121","valorLiquido":150.0,"valorGlosa":0.0,"numRessarcimento":"","codLote":1767043,"parcela":0}],"links":[{"rel":"self","href":"https://dadosabertos.camara.leg.br/api/v2/deputados/178985/despesas?ano=2021&itens=10000"},{"rel":"next","href":"https://dadosabertos.camara.leg.br/api/v2/deputados/178985/despesas?ano=2021&pagina=2&itens=100"},{"rel":"first","href":"https://dadosabertos.camara.leg.br/api/v2/deputados/178985/despesas?ano=2021&pagina=1&itens=100"},{"rel":"last","href":"https://dadosabertos.camara.leg.br/api/v2/deputados/178985/despesas?ano=2021&pagina=7&itens=100"}]}
